Workbook
Name Brebis: ANIMAL!$D$24:$D$26
Name Céréale: COUT!$Q$29:$Q$36
Name Divers: COUT!$Q$55:$Q$63
Name Fibres: COUT!$Q$82:$Q$89
Name Graines: COUT!$Q$45:$Q$53
Name Mél: FOURRAGE!A1
Name Melange: MELANGE!$A$1
Name Mes_concentrés: NOUVEAU!$R$22:$R$36
Name Minéraux: COUT!$Q$65:$Q$80
Name Tourteau: COUT!$Q$38:$Q$43

Sheet ALIMOVINS
B1: fabrice.ranoux@educagri.fr
B3: Rationnement des ovins
B4: Fabrice RANOUX - LYCEE AGRICOLE du BOURBONNAIS - BP 1721 - 03017 MOULINS cedex - Tous droits réservés
B10: Version utilisable avec Microsoft® Excel 2010 et au-delà
C11: Code de déverrouillage → ctrl

Sheet ACCUEIL
B2: ALIM'ovins(v. 5.1)
B3: Rationnement des ovins
B4: Fabrice RANOUX - Lycée Agricole du Bourbonnais - BP 1721 - 03017 MOULINS cedex - Tous droits réservés
C7: RATION | E7: Etablissement d'une ration | H7: Cliquez
C10: BILAN | E10: Bilan alimentaire et coût | H10: Cliquez
C13: COUT | E13: Formulation d'aliment et coût de concentré | H13: Cliquez
C16: PREVISION | E16: Prévision de la valeur alimentaire des aliments du commerce | H16: Cliquez
C19: ALIMENTS | E19: Saisie de mes nouveaux aliments | H19: Cliquez
C22: FOURRAGES | E22: Bilan fourrager du troupeau | H22: Cliquez
C25: AGNEAUX | E25: Besoins des agneaux à l'engrais | H25: Cliquez
C28: PATURAGE | E28: Jours d'avance de pâturage | H28: Cliquez
C30: Les saisies effectuent uniquement dans les cases "blanches"
C31: Les cases "bleues" correspondent à des menus déroulants

Sheet PREVISION
B2: ALIM'ovins(v. 5.1)
B3: Rationnement des ovins
C5: Prévision
A7: Prévision de la valeur alimentaire d'un concentré du commerce (à partir des constituants analytiques)
B9: Valeurs d'analyse pour 100 g | D9: Saisissez les constituants | I9: Valeurs calculées | M9: Valeurs d'analyse
B10: Calculs effectués à partir des équations INRA | I10: MS | J10: =IF(D12="","",100-D12) | K10: % | N10: Saisissez les constituants
B12: Humidité | F12: % | I12: UFL | J12: =IF(D12="","",((118+(0.256*D14)+(1.58*D16)-(1.02*D18)-(2.07*I27))*(J10/10000))*(C36/1000)) | M12: P (Phosphore) | O12: %
B14: Protéines Brutes (Matières Azotées Totales) | C14: MAT | F14: % | I14: UFV | J14: =IF(D12="","",((120+(0.214*D14)+(1.62*D16)-(1.19*D18)-(2.64*I27))*(J10/10000))*(C36/1000)) | M14: Ca (Calcium) | O14: %
B16: Matière Grasse (Lipides) | C16: MG | F16: % | I16: PDIA | J16: =IF(D12="","",C30*(J10/100)) | K16: g / kg | M16: Minéraux absorbables
B18: Cellulose Brute | C18: CB | F18: % | I18: PDIN | J18: =IF(D12="","",C31*(J10/100)) | K18: g / kg | M18: Pabs | N18: =IF(N12="","",N12*6.5) | O18: g/100 g
B20: Cendres Brutes (Matières Minérales) | C20: MM | F20: % | I20: PDIE | J20: =IF(D12="","",C32*(J10/100)) | K20: g / kg | M20: Ca abs | N20: =IF(N14="","",N14*4) | O20: g/100 g
J22: =IF(D22="","",D22*0.7) | K22: =IF(J22="","","g / kg brut")
B27: MAT | C27: =D14*10 -> 0 | I27: =IF(D14>25,6,IF(D14>20,4,2)) -> 2
B28: DE1 | C28: 34
B29: MANDE1 | C29: =C27*(1-(C28/100)) -> 0
B30: PDIA | C30: =(-0.211*C27)+(0.84*C29) -> 0
B31: PDIN | C31: =(0.507*C27)+(0.278*C29) -> 0
B32: PDIE | C32: =67.1-(0.22*C27)+(0.802*C29) -> 67.1
B33: MG | C33: =D16*10 -> 0
B34: CB | C34: =D18*10 -> 0
B35: MM | C35: =D20*10 -> 0
B36: MO | C36: =1000-C35 -> 1000
B37: EB

Sheet ANIMAL
B1: ALIM'ovins(v. 5.1)
B2: Rationnement des ovins
F4: Ration
C6: 1 Cliquez sur les flèches pour faire votre choix | L6: REPARTITION DES BESOINS | R6: =R8-R7 -> 0.34138499 | S6: =S8-S7 -> 0.29946052 | T6: =T8-T7 -> 85.498863 | U6: =U8-U7 -> 0.58560865
R7: =POWER(C23,0.75)*0.033 -> 0.79861501 | S7: =R7/R8 -> 0.70053948 | T7: =POWER(C23,0.75)*2.5 -> 60.501137 | U7: =T7/T8 -> 0.41439135
B8: Catégorie animal | C8: Brebis | E8: BESOINS ALIMENTAIRES | M8: U.F.L. | O8: P.D.I. | R8: =F16 -> 1.14 | S8: 1 | T8: =G16 -> 146 | U8: 1
B10: Poids vif | C10: =IF(C8="","",CONCATENATE(C23," kg")) -> 70 kg | E10: CATEGORIE | L10: en % des besoins totaux
E11: =CONCATENATE(C8," ",C10," ",C12," ",C14," ",C16) -> Brebis 70 kg Gestante Double Semaines - 3 à - 4 | L11: ENTRETIEN
B12: =IF(C8="Brebis traite","Production laitière",IF(C8="brebis","Stade physiologique","Objectifs")) -> Stade physiologique | C12: Gestante
L13: =CONCATENATE(ROUND(G16/F16,0)," g PDI/UF") -> 128 g PDI/UF
B14: =IF(C8="Brebis","Agnelage Etat","") -> Agnelage Etat | C14: Double | E14: APPORTS ALIMENTAIRES RECOMMANDES
E15: U.E.M | F15: U.F.L | G15: P.D.I. | H15: Pabs | I15: Caabs | L15: PRODUCTION
B16: =IF(C8="Brebis","Période (semaines)","") -> Période (semaines) | C16: Semaines - 3 à - 4 | E16: =IF(C8="","",VLOOKUP($E$11,$C$39:$I$393,3)) -> 1.71 | F16: =IF(C8="","",IF(VLOOKUP($E$11,$C$39:$I$393,4)="ND","ND",IF(E34=2,VLOOKUP($E$11,$C$39:$I$393,4),VLOOKUP($E$11,$C$39:$I$393,4)+0.2))) -> 1.14 | G16: =IF(C8="","",VLOOKUP($E$11,$C$39:$I$393,5)) -> 146 | H16: =IF(C8="","",VLOOKUP($E$11,$C$39:$I$393,6)) -> 3.2 | I16: =IF(C8="","",VLOOKUP($E$11,$C$39:$I$393,7)) -> 3.5
C17: ND: non disponible | E17: =CONCATENATE(ROUND(F16/E16,2)," UFL / UEM") -> 0.67 UFL / UEM | G17: =CONCATENATE(ROUND(G16/F16,0)," g PDI / UFL") -> 128 g PDI / UFL | I17: =CONCATENATE("Ca/P = ",ROUND(I16/H16,1)) -> Ca/P = 1.1
C23: 70 | I23: 30 kg
C24: Brebis | D24: =IF(C8="Brebis traite","0,5 l/jour",IF(C8="Brebis","Allaitante","Croissance")) -> Allaitante | E24: =IF(C12="Engrais","Mauvais état (1 - 1.5)",IF(C8="Bélier","",IF(C8="Agnelle","",IF(C8="Brebis traite","",IF(C12="Vide","Sans prise de poids - Entretien",IF(C12="gestante",D31,F31)))))) -> Semaines - 5 à - 6 | F24: =IF(C12="Engrais","GMQ 50 g/j",IF(C8="Bélier","",IF(C8="Agnelle","",IF(C8="Brebis traite","",IF(C12="Vide","Mauvais Etat (< 2,5)","Simple"))))) -> Simple | I24: 40 kg
C25: Bélier | D25: =IF(C8="Brebis traite","1,0 l/jour",IF(C8="Brebis","Gestante","Flushing")) -> Gestante | E25: =IF(C12="Engrais","Etat moyen (2 - 2.5)",IF(C8="Bélier","",IF(C8="Agnelle","",IF(C8="Brebis traite","",IF(C12="Vide","Avec prise de poids + 150 g/j",IF(C12="gestante",D32,F32)))))) -> Semaines - 3 à - 4 | F25: =IF(C12="Engrais","GMQ 100 g/j",IF(C8="Bélier","",IF(C8="Agnelle","",IF(C8="Brebis traite","",IF(C12="Vide","Etat Moyen (2,5 - 3,5)","Double"))))) -> Double | I25: 50 kg | J25: 30 kg | K25: 70 kg
C26: Agnelle | D26: =IF(C8="Brebis traite","2,0 l/jour",IF(C8="Brebis","Vide","Entretien")) -> Vide | E26: =IF(C12="Engrais","Bon état (3 - 3.5)",IF(C8="Bélier","",IF(C8="Agnelle","",IF(C8="Brebis traite","",IF(C12="Vide","flushing + 100 g/j",IF(C12="gestante",D33,F33)))))) -> Semaines - 2 à 0 | F26: =IF(C12="Engrais","GMQ 150 g/j",IF(C8="Bélier","",IF(C8="Agnelle","",IF(C8="Brebis traite","",IF(C12="Vide","Bon Etat (> 3,5)",IF(C12="Allaitante","Triple","Inconnu")))))) -> Inconnu | I26: 60 kg | J26: 40 kg | K26: 80 kg
C27: Brebis traite | D27: =IF(C8="Brebis traite","2,5 l/jour",IF(C8="Brebis","Engrais","")) -> Engrais | I27: 70 kg | J27: 50 kg | K27: 90 kg
D28: =IF(C8="Brebis traite","3,0 l/jour","") | I28: 80 kg | K28: 100 kg
C29: 60 kg | D29: =IF(C8="Brebis traite","3,5 l/jour","") | I29: 90 kg
C30: =IF($C$9="brebis",I25,IF($C$9="Agnelle",J25,K25)) -> 70 kg | I30: 100 kg
C31: =IF($C$9="brebis",I26,IF($C$9="Agnelle",J26,K26)) -> 80 kg | D31: Semaines - 5 à - 6 | F31: Semaines 0 à + 3
C32: =IF($C$9="brebis",I27,IF($C$9="Agnelle",J27,K27)) -> 90 kg | D32: Semaines - 3 à - 4 | F32: Semaines + 4 à + 6
C33: =IF($C$9="brebis",I28,IF($C$9="Agnelle",J28,K28)) -> 100 kg | D33: Semaines - 2 à 0 | F33: Semaines + 7 à + 10 | I33: Bergerie
E34: 2 | I34: Plein air
C38: Catégorie | E38: UEM | F38: UFL | G38: PDI | H38: Pabs | I38: Caabs
C39: Agnelle 100 kg Croissance | E39: ND | F39: ND | G39: ND | H39: ND | I39: ND
C40: Agnelle 100 kg Entretien | E40: ND | F40: ND | G40: ND | H40: ND | I40: ND
C41: Agnelle 100 kg Flushing | E41: ND | F41: ND | G41: ND | H41: ND | I41: ND
C42: Agnelle 30 kg Croissance | D42: 13 | E42: 1 | F42: 0.57 | G42: 52 | H42: 0.9 | I42: 1
C43: Agnelle 30 kg Entretien | D43: 15 | E43: 1 | F43: 0.44 | G43: 32 | H43: 0.6 | I43: 0.8
C44: Agnelle 30 kg Flushing | D44: 14 | E44: 1 | F44: 1 | G44: 54 | H44: 0.6 | I44: 0.8
C45: Agnelle 40 kg Croissance | D45: 16 | E45: 1.2 | F45: 0.78 | G45: 62 | H45: 1.4 | I45: 1.5
C46: Agnelle 40 kg Entretien | D46: 18 | E46: 1.2 | F46: 0.52 | G46: 40 | H46: 0.8 | I46: 1
C47: Agnelle 40 kg Flushing | D47: 17 | E47: 1.2 | F47: 1.08 | G47: 62 | H47: 0.8 | I47: 1
C48: Agnelle 50 kg Croissance | D48: 19 | E48: 1.3 | F48: 0.84 | G48: 69 | H48: 1.6 | I48: 1.7
C49: Agnelle 50 kg Entretien | D49: 21 | E49: 1.3 | F49: 0.62 | G49: 47 | H49: 1 | I49: 1.2
C50: Agnelle 50 kg Flushing | D50: 20 | E50: 1.3 | F50: 0.84 | G50: 69 | H50: 1 | I50: 1.2
C51: Agnelle 60 kg Croissance | E51: ND | F51: ND | G51: ND | H51: ND | I51: ND
C52: Agnelle 60 kg Entretien | E52: ND | F52: ND | G52: ND | H52: ND | I52: ND
C53: Agnelle 60 kg Flushing | E53: ND | F53: ND | G53: ND | H53: ND | I53: ND
C54: Agnelle 70 kg Croissance | E54: ND | F54: ND | G54: ND | H54: ND | I54: ND
C55: Agnelle 70 kg Entretien | E55: ND | F55: ND | G55: ND | H55: ND | I55: ND
C56: Agnelle 70 kg Flushing | E56: ND | F56: ND | G56: ND | H56: ND | I56: ND
C57: Agnelle 80 kg Croissance | E57: ND | F57: ND | G57: ND | H57: ND | I57: ND
C58: Agnelle 80 kg Entretien | E58: ND | F58: ND | G58: ND | H58: ND | I58: ND
C59: Agnelle 80 kg Flushing | E59: ND | F59: ND | G59: ND | H59: ND | I59: ND
C60: Agnelle 90 kg Croissance | E60: ND | F60: ND | G60: ND | H60: ND | I60: ND
C61: Agnelle 90 kg Entretien | E61: ND | F61: ND | G61: ND | H61: ND | I61: ND
C62: Agnelle 90 kg Flushing | E62: ND | F62: ND | G62: ND | H62: ND | I62: ND
C63: Bélier 100 kg Croissance | D63: 10 | E63: ND | F63: ND | G63: ND | H63: ND | I63: ND
C64: Bélier 100 kg Entretien | D64: 12 | E64: 2.8 | F64: 1.1 | G64: 88 | H64: 2.2 | I64: 2.9
C65: Bélier 100 kg Flushing | D65: 11 | E65: 2.8 | F65: 1.66 | G65: 110 | H65: 2.2 | I65: 2.9
C66: Bélier 30 kg Croissance | E66: ND | F66: ND | G66: ND | H66: ND | I66: ND
C67: Bélier 30 kg Entretien | E67: ND | F67: ND | G67: ND | H67: ND | I67: ND
C68: Bélier 30 kg Flushing | E68: ND | F68: ND | G68: ND | H68: ND | I68: ND
C69: Bélier 40 kg Croissance | E69: ND | F69: ND | G69: ND | H69: ND | I69: ND
C70: Bélier 40 kg Entretien | E70: ND | F70: ND | G70: ND | H70: ND | I70: ND
C71: Bélier 40 kg Flushing | E71: ND | F71: ND | G71: ND | H71: ND | I71: ND
C72: Bélier 50 kg Croissance | E72: 1.8 | F72: 1.11 | G72: 86 | H72: 1.9 | I72: 2.4
C73: Bélier 50 kg Entretien | E73: 1.8 | F73: 0.72 | G73: 63 | H73: 1.2 | I73: 1.4
C74: Bélier 50 kg Flushing | E74: 1.8 | F74: 1.29 | G74: 75 | H74: 1.2 | I74: 2.7
C75: Bélier 60 kg Croissance | E75: 2 | F75: 1.19 | G75: 93 | H75: 2.1 | I75: 2.7
C76: Bélier 60 kg Entretien | E76: 2 | F76: 0.8 | G76: 60 | H76: 1.4 | I76: 1.7
C77: Bélier 60 kg Flushing | E77: 2 | F77: 1.36 | G77: 82 | H77: 1.4 | I77: 3
C78: Bélier 70 kg Croissance | D78: 1 | E78: 2.2 | F78: 1.27 | G78: 100 | H78: 2.3 | I78: 3
C79: Bélier 70 kg Entretien | D79: 3 | E79: 2.2 | F79: 0.88 | G79: 67 | H79: 1.6 | I79: 2
C80: Bélier 70 kg Flushing | D80: 2 | E80: 2.2 | F80: 1.44 | G80: 89 | H80: 1.6 | I80: 2
C81: Bélier 80 kg Croissance | D81: 4 | E81: 2.4 | F81: 1.35 | G81: 107 | H81: 2.5 | I81: 3.3
C82: Bélier 80 kg Entretien | D82: 6 | E82: 2.4 | F82: 0.96 | G82: 74 | H82: 1.8 | I82: 2.3
C83: Bélier 80 kg Flushing | D83: 5 | E83: 2.4 | F83: 1.52 | G83: 96 | H83: 1.8 | I83: 2.3
C84: Bélier 90 kg Croissance | D84: 7 | E84: ND | F84: ND | G84: ND | H84: ND | I84: ND
C85: Bélier 90 kg Entretien | D85: 9 | E85: 2.6 | F85: 1.04 | G85: 81 | H85: 2 | I85: 2.6
C86: Bélier 90 kg Flushing | D86: 8 | E86: 2.6 | F86: 1.6 | G86: 103 | H86: 2 | I86: 2.6
C87: Brebis 100 kg Allaitante Double Semaines + 4 à + 6 | D87: 116 | E87: ND | F87: ND | G87: ND | H87: ND | I87: ND
C88: Brebis 100 kg Allaitante Double Semaines + 7 à + 10 | D88: 117 | E88: ND | F88: ND | G88: ND | H88: ND | I88: ND
C89: Brebis 100 kg Allaitante Double Semaines 0 à + 3 | D89: 115 | E89: ND | F89: ND | G89: ND | H89: ND | I89: ND
C90: Brebis 100 kg Allaitante Simple Semaines + 4 à + 6 | D90: 113 | E90: ND | F90: ND | G90: ND | H90: ND | I90: ND
C91: Brebis 100 kg Allaitante Simple Semaines + 7 à + 10 | D91: 114 | E91: ND | F91: ND | G91: ND | H91: ND | I91: ND
C92: Brebis 100 kg Allaitante Simple Semaines 0 à + 3 | D92: 112 | E92: ND | F92: ND | G92: ND | H92: ND | I92: ND
C93: Brebis 100 kg Gestante Double Semaines - 2 à 0 | D93: 90 | E93: ND | F93: ND | G93: ND | H93: ND | I93: ND
C94: Brebis 100 kg Gestante Double Semaines - 3 à - 4 | D94: 89 | E94: ND | F94: ND | G94: ND | H94: ND | I94: ND
C95: Brebis 100 kg Gestante Double Semaines - 5 à - 6 | D95: 88 | E95: ND | F95: ND | G95: ND | H95: ND | I95: ND
C96: Brebis 100 kg Gestante Inconnu Semaines - 2 à 0 | D96: 93 | E96: ND | F96: ND | G96: ND | H96: ND | I96: ND
C97: Brebis 100 kg Gestante Inconnu Semaines - 3 à - 4 | D97: 92 | E97: ND | F97: ND | G97: ND | H97: ND | I97: ND
C98: Brebis 100 kg Gestante Inconnu Semaines - 5 à - 6 | D98: 91 | E98: ND | F98: ND | G98: ND | H98: ND | I98: ND
... C116: Brebis 30 kg Allaitante Simple Semaines 0 à + 3 | D116: 112 | E116: ND | F116: ND | G116: ND | H116: ND | I116: ND
C117: Brebis 30 kg Allaitante Triple Semaines + 4 à + 6 | E117: ND | F117: ND | G117: ND | H117: ND | I117: ND
C118: Brebis 30 kg Allaitante Triple Semaines + 7 à + 10 | E118: ND | F118: ND | G118: ND | H118: ND | I118: ND
C119: Brebis 30 kg Allaitante Triple Semaines 0 à + 3 | E119: ND | F119: ND | G119: ND | H119: ND | I119: ND
C120: Brebis 30 kg Gestante Double Semaines - 2 à 0 | D120: 90 | E120: ND | F120: ND | G120: ND | H120: ND | I120: ND
C121: Brebis 30 kg Gestante Double Semaines - 3 à - 4 | D121: 89 | E121: ND | F121: ND | G121: ND | H121: ND | I121: ND
C122: Brebis 30 kg Gestante Double Semaines - 5 à - 6 | D122: 88 | E122: ND | F122: ND | G122: ND | H122: ND | I122: ND
C123: Brebis 30 kg Gestante Inconnu Semaines - 2 à 0 | D123: 93 | E123: ND | F123: ND | G123: ND | H123: ND | I123: ND
C124: Brebis 30 kg Gestante Inconnu Semaines - 3 à - 4 | D124: 92 | E124: ND | F124: ND | G124: ND | H124: ND | I124: ND
C125: Brebis 30 kg Gestante Inconnu Semaines - 5 à - 6 | D125: 91 | E125: ND | F125: ND | G125: ND | H125: ND | I125: ND
C126: Brebis 30 kg Gestante Simple Semaines - 2 à 0 | D126: 87 | E126: ND | F126: ND | G126: ND | H126: ND | I126: ND
C127: Brebis 30 kg Gestante Simple Semaines - 3 à - 4 | D127: 86 | E127: ND | F127: ND | G127: ND | H127: ND | I127: ND
C128: Brebis 30 kg Gestante Simple Semaines - 5 à - 6 | D128: 85 | E128: ND | F128: ND | G128: ND | H128: ND | I128: ND
...

Sheet FOURRAGE
B1: ALIM'ovins(v. 5.1)
B2: Rationnement des ovins
H4: Ration
B5: zone de Plaine (Normandie) zone de Demi-montagne (Auvergne)
E6: FOURRAGE N° 1 (Rationné ou à volonté) | K6: 2 Saisissez les quantités brutes ou cliquez A VOLONTE
O7: =IF(ANIMAL!C8="","",IF(O11>1,"ATTENTION ! La capacité d'ingestion est dépassée",IF(C9="","",IF(V7<0.02,"La capacité d'ingestion est atteinte","La capacité d'ingestion n'est pas atteinte")))) -> ATTENTION ! La capacité d'ingestion est dépassée | U7: =ANIMAL!E16 -> 1.71 | V7: =IF(O11>1,0,1-V9-V8) -> 0
B8: 1 Cliquez sur les flèches pour faire votre choix | U8: =IF(C23="",0,L24*(E29/100)*F29) -> 0 | V8: =IF(O11>1,0,U8/U7) -> 0
B9: Catégorie fourrage | E9: =CONCATENATE(C9," ",C11," ",C13," ",C15) | O9: Capacité d'ingestion | T9: =U12/U7 -> 0 | U9: =IF(C9="",0,(L10*(E15/100)*F15)) -> 0 | V9: =IF(O11>1,0,U9/U7) -> 0
Q10: =IF(O11="","",IF(O11>1,"Réduisez les fourrages !",""))
B11: Espèce végétale | O11: =IF(C9="","",T9)
O12: =IF(C23="","",C23) | Q12: =IF(C23="","",2) | U12: =U9+U8 -> 0 | V12: =U12/U7 -> 0
B13: Conditions de récolte | E13: Valeurs Alimentaires
E14: % M.S. | F14: U.E.M. | G14: U.F.L | H14: P.D.I.N. | I14: P.D.I.E. | J14: Pabs | L14: Caabs | O14: =IF(C9="","",C9) | Q14: =IF(C9="","",1)
B15: Stade physiologique | E15: =IF(B42=1,IF(C9="","",IF(C9="Mon fourrage",VLOOKUP($C$11,NOUVEAU!$E$22:$N30,3),VLOOKUP($E$9,$C$78:L246,2))),IF(C9="","",IF(C9="Mon fourrage",VLOOKUP($C$11,NOUVEAU!$E$22:$N30,3),VLOOKUP($E$9,$C$259:L433,2)))) | F15: =IF(B42=1,IF(C9="","",IF(C9="Mon fourrage",VLOOKUP($C$11,NOUVEAU!$E$22:$N30,4),VLOOKUP($E$9,$C$78:M246,3))),IF(C9="","",IF(C9="Mon fourrage",VLOOKUP($C$11,NOUVEAU!$E$22:$N30,4),VLOOKUP($E$9,$C$259:M433,3)))) | G15: =IF(B42=1,IF(C9="","",IF(C9="Mon fourrage",VLOOKUP($C$11,NOUVEAU!$E$22:$N30,5),VLOOKUP($E$9,$C$78:N246,5))),IF(C9="","",IF(C9="Mon fourrage",VLOOKUP($C$11,NOUVEAU!$E$22:$N30,5),VLOOKUP($E$9,$C$259:N433,5)))) | H15: =IF(B42=1,IF(C9="","",IF(C9="Mon fourrage",VLOOKUP($C$11,NOUVEAU!$E$22:$N30,7),VLOOKUP($E$9,$C$78:O246,7))),IF(C9="","",IF(C9="Mon fourrage",VLOOKUP($C$11,NOUVEAU!$E$22:$N30,7),VLOOKUP($E$9,$C$259:O433,7)))) | I15: =IF(B42=1,IF(C9="","",IF(C9="Mon fourrage",VLOOKUP($C$11,NOUVEAU!$E$22:$N30,8),VLOOKUP($E$9,$C$78:P246,8))),IF(C9="","",IF(C9="Mon fourrage",VLOOKUP($C$11,NOUVEAU!$E$22:$N30,8),VLOOKUP($E$9,$C$259:P433,8)))) | J15: =IF(B42=1,IF(C9="","",IF(C9="Mon fourrage",VLOOKUP($C$11,NOUVEAU!$E$22:$N30,9),VLOOKUP($E$9,$C$78:Q246,9))),IF(C9="","",IF(C9="Mon fourrage",VLOOKUP($C$11,NOUVEAU!$E$22:$N30,9),VLOOKUP($E$9,$C$259:Q433,9)))) | K15: =IF(B9="","",IF(B9="Mon fourrage",VLOOKUP($C$11,NOUVEAU!$E$22:$N31,10),VLOOKUP($E$9,$C$78:R246,10))) -> #N/A | L15: =IF(B42=1,IF(C9="","",IF(C9="Mon fourrage",VLOOKUP($C$11,NOUVEAU!$E$22:$N30,10),VLOOKUP($E$9,$C$78:S246,10))),IF(C9="","",IF(C9="Mon fourrage",VLOOKUP($C$11,NOUVEAU!$E$22:$N30,10),VLOOKUP($E$9,$C$259:S433,10))))
E16: ND: non disponible
E20: FOURRAGE N° 2 (Rationné)
B21: 1 Cliquez sur les flèches pour faire votre choix | K21: 3 Saisissez les quantités brutes | O21: Densité énergétique de la ration minimale
B23: Catégorie fourrage | E23: =CONCATENATE(C23," ",C25," ",C27," ",C29) | O23: DERm | Q23: =IF(ANIMAL!C8="","",ANIMAL!F16/ANIMAL!E16) -> 0.66666667
B25: Espèce végétale | O25: =IF(C23="","",IF(Q23>Q27,">","<")) | P25: Densité énergétique du fourrage
B27: Conditions de récolte | E27: Valeurs Alimentaires | O27: DEF | Q27: =IF(C9="","",IF(L24="",G15/F15,AVERAGE((G15/F1),(G29/F29))))
E28: % M.S. | F28: U.E.M | G28: U.F.L | H28: P.D.I.N. | I28: P.D.I.E. | J28: Pabs | L28: Caabs | O28: =IF(C9="","",IF(Q23>Q27,"Il faut ajouter un concentré","Un concentré n'est pas nécessaire"))
B29: Stade physiologique | E29: =IF(B42=1,IF(C23="","",IF(C23="Mon fourrage",VLOOKUP($C$25,NOUVEAU!$E$22:$N30,3),VLOOKUP($E$23,$C$78:L246,2))),IF(C23="","",IF(C23="Mon fourrage",VLOOKUP($C$25,NOUVEAU!$E$22:$N30,3),VLOOKUP($E$23,$C$259:L433,2)))) | F29: =IF(B42=1,IF(C23="","",IF(C23="Mon fourrage",VLOOKUP($C$25,NOUVEAU!$E$22:$N30,4),VLOOKUP($E$23,$C$78:M246,3))),IF(C23="","",IF(C23="Mon fourrage",VLOOKUP($C$25,NOUVEAU!$E$22:$N30,4),VLOOKUP($E$23,$C$259:M433,3)))) | G29: =IF(B42=1,IF(C23="","",IF(C23="Mon fourrage",VLOOKUP($C$25,NOUVEAU!$E$22:$N30,5),VLOOKUP($E$23,$C$78:N246,5))),IF(C23="","",IF(C23="Mon fourrage",VLOOKUP($C$25,NOUVEAU!$E$22:$N30,5),VLOOKUP($E$23,$C$259:N433,5)))) | H29: =IF(B42=1,IF(C23="","",IF(C23="Mon fourrage",VLOOKUP($C$25,NOUVEAU!$E$22:$N30,7),VLOOKUP($E$23,$C$78:O246,7))),IF(C23="","",IF(C23="Mon fourrage",VLOOKUP($C$25,NOUVEAU!$E$22:$N30,7),VLOOKUP($E$23,$C$259:O433,7)))) | I29: =IF(B42=1,IF(C23="","",IF(C23="Mon fourrage",VLOOKUP($C$25,NOUVEAU!$E$22:$N30,8),VLOOKUP($E$23,$C$78:P246,8))),IF(C23="","",IF(C23="Mon fourrage",VLOOKUP($C$25,NOUVEAU!$E$22:$N30,8),VLOOKUP($E$23,$C$259:P433,8)))) | J29: =IF(B42=1,IF(C23="","",IF(C23="Mon fourrage",VLOOKUP($C$25,NOUVEAU!$E$22:$N30,9),VLOOKUP($E$23,$C$78:Q246,9))),IF(C23="","",IF(C23="Mon fourrage",VLOOKUP($C$25,NOUVEAU!$E$22:$N30,9),VLOOKUP($E$23,$C$259:Q433,9)))) | L29: =IF(B42=1,IF(C23="","",IF(C23="Mon fourrage",VLOOKUP($C$25,NOUVEAU!$E$22:$N30,10),VLOOKUP($E$23,$C$78:S246,10))),IF(C23="","",IF(C23="Mon fourrage",VLOOKUP($C$25,NOUVEAU!$E$22:$N30,10),VLOOKUP($E$23,$C$259:S433,10))))
E30: ND: non disponible
J40: =IF($C$9="Mon fourrage",NOUVEAU!E22,IF($C$9="Paille",Q40,IF($C$9="Ensilage",L40,IF($C$9="Pâture",S40,O40)))) -> Prairie naturelle | L40: Prairie naturelle | O40: Prairie naturelle | Q40: Blé | S40: Pré | U40: Déprimage
B41: =IF(L24="",0,L24*(E29/100)*F29) -> 0 | J41: =IF($C$9="Mon fourrage",NOUVEAU!E23,IF($C$9="Paille",Q41,IF($C$9="Ensilage",L41,IF($C$9="Pâture",S41,O41)))) -> Fétuque élevée | L41: Fétuque | O41: Fétuque élevée | Q41: Orge | S41: Colza fourrager | U41: Printemps
B42: 1 | E42: =IF($C$9="Mon Fourrage","",IF($C$9="Pâture","Déprimage",IF($C$9="Paille","",IF($C$11="Maïs","",L50)))) -> 1er cycle début épiaison (25/05) | J42: =IF($C$9="Mon fourrage",NOUVEAU!E24,IF($C$9="Paille",Q42,IF($C$9="Ensilage",L42,IF($C$9="Pâture",S42,O42)))) -> Luzerne-Dactyle | L42: Luzerne-Dactyle | O42: Luzerne-Dactyle | Q42: Triticale | S42: Betterave (distribuée) | U42: Fin Printemps
C43: Foin | E43: =IF($C$9="Mon Fourrage","",IF($C$9="Pâture","Printemps",IF($C$9="Paille","",IF($C$11="Maïs","",L51)))) -> 1er cycle épaison (10/06) | J43: =IF($C$9="Mon fourrage",NOUVEAU!E25,IF($C$9="Paille",Q43,IF($C$9="Ensilage",L43,IF($C$9="Pâture",S43,O43)))) -> Trèfle-Ray Grass | L43: Trèfle-Ray Grass | O43: Trèfle-Ray Grass | Q43: Avoine | S43: Vesce | U43: Repousses
C44: Ensilage | E44: =IF($C$9="Mon Fourrage","",IF($C$9="Pâture","Fin Printemps",IF($C$9="Paille","",IF($C$11="Maïs","",L52)))) -> 1er cycle début floraison (20/06) | J44: =IF($C$9="Mon fourrage",NOUVEAU!E26,IF($C$9="Paille",Q44,IF($C$9="Ensilage",L44,IF($C$9="Pâture",S44,O44)))) -> Ray Grass Italien | L44: Ray Grass Italien | O44: Ray Grass Italien | Q44: Paille traitée Ammoniac | S44: Trèfle blanc
C45: Paille | E45: =IF($C$9="Mon Fourrage","",IF($C$9="Pâture","Repousse",IF($C$9="Paille","",IF($C$11="Maïs","",L53)))) -> 2ème cycle (regain) | J45: =IF($C$9="Mon fourrage",NOUVEAU!E27,IF($C$9="Paille",Q45,IF($C$9="Ensilage",L45,IF($C$9="Pâture",S45,O45)))) -> Luzerne | L45: Luzerne | O45: Luzerne | S45: Avoine
C46: Pâture | E46: =IF($C$9="Mon Fourrage","",IF($C$9="Pâture","Dérobé",IF($C$9="Paille","",IF($C$11="Maïs","",L54)))) | J46: =IF($C$9="Mon fourrage",NOUVEAU!E28,IF($C$9="Paille",Q46,IF($C$9="Ensilage",L46,IF($C$9="Pâture",S46,O46)))) | L46: Maïs | S46: Navet
C47: Mon fourrage | E47: =IF($C$9="Mon Fourrage","",IF($C$9="Pâture","",IF($C$9="Paille","",IF($C$11="Maïs","",L55))))
D50: Ventilé (en grange) | G50: Ressuyage (25 % MS) | L50: 1er cycle début épiaison (25/05) | P50: Mauvaises conditions < 30 % MS
C51: =IF($C$9="Mon Fourrage","",IF($C$9="Pâture","",IF($C$9="Foin",D50,IF($C$9="Paille","",IF($C$11="Maïs",P50,G50))))) -> Ressuyage (25 % MS) | D51: Fané au sol par beau temps | G51: Préfané (35 % MS) | L51: 1er cycle épaison (10/06) | P51: Conditions normales 25 % MS
C52: =IF($C$9="Mon Fourrage","",IF($C$9="Pâture","",IF($C$9="Foin",D51,IF($C$9="Paille","",IF($C$11="Maïs",P51,G51))))) -> Préfané (35 % MS) | D52: Fané au sol < 10 jours) | G52: Enrubanné (> 45 % MS) | L52: 1er cycle début floraison (20/06) | P52: Conditions normales 30 % MS
C53: =IF($C$9="Mon Fourrage","",IF($C$9="Pâture","",IF($C$9="Foin",D52,IF($C$9="Paille","",IF($C$11="Maïs",P52,G52))))) -> Enrubanné (> 45 % MS) | L53: 2ème cycle (regain) | P53: Conditions normales 35 % MS
C54: =IF($C$9="Mon Fourrage","",IF($C$9="Pâture","",IF($C$9="Foin",D53,IF($C$9="Paille","",IF($C$11="Maïs",P53,G53))))) | P54: Très bonnes conditions (> 35 % MS)
C55: =IF($C$9="Mon Fourrage","",IF($C$9="Pâture","",IF($C$9="Foin",D54,IF($C$9="Paille","",IF($C$11="Maïs",P54,G54))))) | E55: Fourrage 1
C56: =IF($C$9="Pâture","",IF($C$9="Foin",D55,IF($C$9="Paille","",IF($C$11="Maïs",P55,G55)))) | E56: Fourrage 2
E57: Fourrage 3 | J57: =IF($C$23="mon fourrage",NOUVEAU!E22,IF($C$23="Paille",Q57,IF($C$23="Ensilage",L57,IF($C$23="Pâture",S57,O57)))) -> Prairie naturelle | L57: Prairie naturelle | O57: Prairie naturelle | Q57: Blé | S57: Pré | U57: Déprimage
J58: =IF($C$23="mon fourrage",NOUVEAU!E23,IF($C$23="Paille",Q58,IF($C$23="Ensilage",L58,IF($C$23="Pâture",S58,O58)))) -> Fétuque élevée | L58: Fétuque | O58: Fétuque élevée | Q58: Orge | S58: Colza fourrager | U58: Printemps
E59: =IF($C$23="Mon Fourrage","",IF($C$23="Pâture","Déprimage",IF($C$23="Paille","",IF($C$25="Maïs","",L67)))) -> 1er cycle début épiaison (25/05) | J59: =IF($C$23="mon fourrage",NOUVEAU!E24,IF($C$23="Paille",Q59,IF($C$23="Ensilage",L59,IF($C$23="Pâture",S59,O59)))) -> Luzerne-Dactyle | L59: Luzerne-Dactyle | O59: Luzerne-Dactyle | Q59: Triticale | S59: Betterave (distribuée) | U59: Fin Printemps
C60: Foin | E60: =IF($C$23="Mon Fourrage","",IF($C$23="Pâture","Printemps",IF($C$23="Paille","",IF($C$25="Maïs","",L68)))) -> 1er cycle épaison (10/06) | J60: =IF($C$23="mon fourrage",NOUVEAU!E25,IF($C$23="Paille",Q60,IF($C$23="Ensilage",L60,IF($C$23="Pâture",S60,O60)))) -> Trèfle-Ray Grass | L60: Trèfle-Ray Grass | O60: Trèfle-Ray Grass | Q60: Avoine | S60: Vesce | U60: Repousses
C61: Ensilage | E61: =IF($C$23="Mon Fourrage","",IF($C$23="Pâture","Fin Printemps",IF($C$23="Paille","",IF($C$25="Maïs","",L69)))) -> 1er cycle début floraison (20/06) | J61: =IF($C$23="mon fourrage",NOUVEAU!E26,IF($C$23="Paille",Q61,IF($C$23="Ensilage",L61,IF($C$23="Pâture",S61,O61)))) -> Ray Grass Italien | L61: Ray Grass Italien | O61: Ray Grass Italien | Q61: Paille traitée Ammoniac | S61: Trèfle blanc
C62: Paille | E62: =IF($C$23="Mon Fourrage","",IF($C$23="Pâture","Repousse",IF($C$23="Paille","",IF($C$25="Maïs","",L70)))) -> 2ème cycle (regain) | J62: =IF($C$23="mon fourrage",NOUVEAU!E27,IF($C$23="Paille",Q62,IF($C$23="Ensilage",L62,IF($C$23="Pâture",S62,O62)))) -> Luzerne | L62: Luzerne | O62: Luzerne | S62: Avoine
C63: Pâture | E63: =IF($C$23="Mon Fourrage","",IF($C$23="Pâture","Dérobé",IF($C$23="Paille","",IF($C$25="Maïs","",L71)))) | J63: =IF($C$23="Paille",Q63,IF($C$23="Ensilage",L63,IF($C$23="Pâture",S63,O63))) | L63: Maïs | S63: Navet
C64: Mon fourrage | E64: =IF($C$23="Mon Fourrage","",IF($C$23="Pâture","",IF($C$23="Paille","",IF($C$25="Maïs","",L72))))
E65: =IF($C$23="Pâture","",IF($C$23="Paille","",IF($C$25="Maïs","",L73)))
D67: Ventilé (en grange) | G67: Ressuyage (25 % MS) | L67: 1er cycle début épiaison (25/05) | P67: Mauvaises conditions < 30 % MS
C68: =IF($C$23="Mon Fourrage","",IF($C$23="Pâture","",IF($C$23="Foin",D67,IF($C$23="Paille","",IF($C$25="Maïs",P67,G67))))) -> Ressuyage (25 % MS) | D68: Fané au sol par beau temps | G68: Préfané (35 % MS) | L68: 1er cycle épaison (10/06) | P68: Conditions normales 25 % MS
C69: =IF($C$23="Mon Fourrage","",IF($C$23="Pâture","",IF($C$23="Foin",D68,IF($C$23="Paille","",IF($C$25="Maïs",P68,G68))))) -> Préfané (35 % MS) | D69: Fané au sol < 10 jours) | G69: Enrubanné (> 45 % MS) | L69: 1er cycle début floraison (20/06) | P69: Conditions normales 30 % MS
C70: =IF($C$23="Mon Fourrage","",IF($C$23="Pâture","",IF($C$23="Foin",D69,IF($C$23="Paille","",IF($C$25="Maïs",P69,G69))))) -> Enrubanné (> 45 % MS) | L70: 2ème cycle (regain) | P70: Conditions normales 35 % MS
C71: =IF($C$23="Mon Fourrage","",IF($C$23="Pâture","",IF($C$23="Foin",D70,IF($C$23="Paille","",IF($C$25="Maïs",P70,G70))))) | P71: Très bonnes conditions (> 35 % MS)
C72: =IF($C$23="Mon Fourrage","",IF($C$23="Pâture","",IF($C$23="Foin",D71,IF($C$23="Paille","",IF($C$25="Maïs",P71,G71)))))
D77: % MS | E77: UEM | F77: UEB | G77: UFL | H77: UFV | I77: PDIN | J77: PDIE | K77: Pabs | L77: Caabs
C78: Betterave fourragère | D78: 13 | E78: 0.91 | F78: 1.2 | G78: 1.15 | H78: 1.16 | I78: 62 | J78: 86 | K78: 1.1 | L78: 0.5
C79: Ensilage Fétuque Enrubanné (> 45 % MS) 1er cycle épaison (10/06) | D79: 55 | E79: 1.53 | F79: 1.26 | G79: 0.67 | H79: 0.59 | I79: 66 | J79: 68 | K79: 1.4 | L79: 1.3 | M79: 27
C80: Ensilage Fétuque Enrubanné (> 45 % MS) 1er cycle début épiaison (25/05) | D80: 55 | E80: 1.41 | F80: 1.14 | G80: 0.73 | H80: 0.65 | I80: 82 | J80: 75 | K80: 1.6 | L80: 1.3 | M80: 26
C81: Ensilage Fétuque Enrubanné (> 45 % MS) 1er cycle début floraison (20/06) | D81: ND | E81: ND | F81: ND | G81: ND | H81: ND | I81: ND | J81: ND | K81: ND | L81: ND | M81: 28
C82: Ensilage Fétuque Enrubanné (> 45 % MS) 2ème cycle (regain) | D82: 55 | E82: 1.4 | F82: 1.13 | G82: 0.71 | H82: 0.63 | I82: 85 | J82: 77 | K82: 1.8 | L82: 1.8 | M82: 29
C83: Ensilage Fétuque Préfané (35 % MS) 1er cycle épaison (10/06) | D83: 33 | E83: 1.76 | F83: 1.23 | G83: 0.67 | H83: 0.58 | I83: 69 | J83: 58 | K83: 1.4 | L83: 1.3 | M83: 23
C84: Ensilage Fétuque Préfané (35 % MS) 1er cycle début épiaison (25/05) | D84: 33 | E84: 1.48 | F84: 1.13 | G84: 0.73 | H84: 0.65 | I84: 83 | J84: 63 | K84: 1.6 | L84: 1.3 | M84: 22
C85: Ensilage Fétuque Préfané (35 % MS) 1er cycle début floraison (20/06) | D85: ND | E85: ND | F85: ND | G85: ND | H85: ND | I85: ND | J85: ND | K85: ND | L85: ND | M85: 24
C86: Ensilage Fétuque Préfané (35 % MS) 2ème cycle (regain) | D86: 33 | E86: 1.46 | F86: 1.12 | G86: 0.72 | H86: 0.64 | I86: 85 | J86: 64 | K86: 1.8 | L86: 1.8 | M86: 25
C87: Ensilage Fétuque Ressuyage (25 % MS) 1er cycle épaison (10/06) | D87: 21 | E87: 1.48 | F87: 1.4 | G87: 0.73 | H87: 0.64 | I87: 65 | J87: 49 | K87: 1.4 | L87: 1.3 | M87: 19
C88: Ensilage Fétuque Ressuyage (25 % MS) 1er cycle début épiaison (25/05) | D88: 21 | E88: 1.39 | F88: 1.31 | G88: 0.79 | H88: 0.72 | I88: 78 | J88: 53 | K88: 1.6 | L88: 1.3 | M88: 18
C89: Ensilage Fétuque Ressuyage (25 % MS) 1er cycle début floraison (20/06) | D89: ND | E89: ND | F89: ND | G89: ND | H89: ND | I89: ND | J89: ND | K89: ND | L89: ND | M89: 20
C90: Ensilage Fétuque Ressuyage (25 % MS) 2ème cycle (regain) | D90: 21 | E90: 1.38 | F90: 1.26 | G90: 0.78 | H90: 0.7 | I90: 81 | J90: 55 | K90: 1.8 | L90: 1.8 | M90: 21
C91: Ensilage Luzerne Enrubanné (> 45 % MS) 1er cycle épaison (10/06) | D91: 55 | E91: 1.2 | F91: 1.07 | G91: 0.67 | H91: 0.57 | I91: 105 | J91: 75 | K91: 1.7 | L91: 3.8 | M91: 75
C92: Ensilage Luzerne Enrubanné (> 45 % MS) 1er cycle début épiaison (25/05) | D92: 55 | E92: 1.19 | F92: 1.07 | G92: 0.71 | H92: 0.62 | I92: 113 | J92: 79 | K92: 1.7 | L92: 3.8 | M92: 74
C93: Ensilage Luzerne Enrubanné (> 45 % MS) 1er cycle début floraison (20/06) | D93: ND | E93: ND | F93: ND | G93: ND | H93: ND | I93: ND | J93: ND | K93: ND | L93: ND | M93: 76
C94: Ensilage Luzerne Enrubanné (> 45 % MS) 2ème cycle (regain) | D94: 55 | E94: 1.17 | F94: 1.08 | G94: 0.7 | H94: 0.61 | I94: 114 | J94: 77 | K94: 1.5 | L94: 3.6 | M94: 77
C95: Ensilage Luzerne Préfané (35 % MS) 1er cycle épaison (10/06) | D95: ND | E95: ND | F95: ND | G95: ND | H95: ND | I95: ND | J95: ND | K95: ND | L95: ND | M95: 71
C96: Ensilage Luzerne Préfané (35 % MS) 1er cycle début épiaison (25/05) | D96: ND | E96: ND | F96: ND | G96: ND | H96: ND | I96: ND | J96: ND | K96: ND | L96: ND | M96: 70
C97: Ensilage Luzerne Préfané (35 % MS) 1er cycle début floraison (20/06) | D97: ND | E97: ND | F97: ND | G97: ND | H97: ND | I97: ND | J97: ND | K97: ND | L97: ND | M97: 72
C98: Ensilage Luzerne Préfané (35 % MS) 2ème cycle (regain) | D98: ND | E98: ND | F98: ND | G98: ND | H98: ND | I98: ND | J98: ND | K98: ND | L98: ND | M98: 73
C99: Ensilage Luzerne Ressuyage (25 % MS) 1er cycle épaison (10/06) | D99: ND | E99: ND | F99: ND | G99: ND | H99: ND | I99: ND | J99: ND | K99: ND | L99: ND | M99: 67
C100: Ensilage Luzerne Ressuyage (25 % MS) 1er cycle début épiaison (25/05) | D100: ND | E100: ND | F100: ND | G100: ND | H100: ND | I100: ND | J100: ND | K100: ND | L100: ND | M100: 66
C101: Ensilage Luzerne Ressuyage (25 % MS) 1er cycle début floraison (20/06) | D101: ND | E101: ND | F101: ND | G101: ND | H101: ND | I101: ND | J101: ND | K101: ND | L101: ND | M101: 68
C102: Ensilage Luzerne Ressuyage (25 % MS) 2ème cycle (regain) | D102: ND | E102: ND | F102: ND | G102: ND | H102: ND | I102: ND | J102: ND | K102: ND | L102: ND | M102: 69
C103: Ensilage Luzerne-Dactyle Enrubanné (> 45 % MS) 1er cycle épaison (10/06) | D103: 55 | E103: 1.37 | F103: 1.16 | G103: 0.69 | H103: 0.6 | I103: 91 | J103: 74 | K103: 1.5 | L103: 2.4 | M103: 39
C104: Ensilage Luzerne-Dactyle Enrubanné (> 45 % MS) 1er cycle début épiaison (25/05) | D104: 55 | E104: 1.26 | F104: 1.07 | G104: 0.76 | H104: 0.68 | I104: 107 | J104: 82 | K104: 1.5 | L104: 2.4 | M104: 38
C105: Ensilage Luzerne-Dactyle Enrubanné (> 45 % MS) 1er cycle début floraison (20/06) | D105: ND | E105: ND | F105: ND | G105: ND | H105: ND | I105: ND | J105: ND | K105: ND | L105: ND | M105: 40
C106: Ensilage Luzerne-Dactyle Enrubanné (> 45 % MS) 2ème cycle (regain) | D106: 55 | E106: 1.27 | F106: 1.09 | G106: 0.71 | H106: 0.62 | I106: 103 | J106: 78 | K106: 1.5 | L106: 2.8 | M106: 41
C107: Ensilage Luzerne-Dactyle Préfané (35 % MS) 1er cycle épaison (10/06) | D107: 33 | E107: 1.16 | F107: 1.12 | G107: 0.73 | H107: 0.64 | I107: 98 | J107: 65 | K107: 1.5 | L107: 2.4 | M107: 35
C108: Ensilage Luzerne-Dactyle Préfané (35 % MS) 1er cycle début épiaison (25/05) | D108: 33 | E108: 1.21 | F108: 1.01 | G108: 0.8 | H108: 0.73 | I108: 113 | J108: 71 | K108: 1.5 | L108: 2.4 | M108: 34
C109: Ensilage Luzerne-Dactyle Préfané (35 % MS) 1er cycle début floraison (20/06) | D109: ND | E109: ND | F109: ND | G109: ND | H109: ND | I109: ND | J109: ND | K109: ND | L109: ND | M109: 32
C110: Ensilage Luzerne-Dactyle Préfané (35 % MS) 2ème cycle (regain) | D110: 33 | E110: 1.23 | F110: 1.04 | G110: 0.73 | H110: 0.64 | I110: 106 | J110: 66 | K110: 1.5 | L110: 2.8 | M110: 37
C111: Ensilage Luzerne-Dactyle Ressuyage (25 % MS) 1er cycle épaison (10/06) | D111: 21 | E111: 1.32 | F111: 1.32 | G111: 0.79 | H111: 0.71 | I111: 90 | J111: 55 | K111: 1.5 | L111: 2.4 | M111: 31
C112: Ensilage Luzerne-Dactyle Ressuyage (25 % MS) 1er cycle début épiaison (25/05) | D112: 21 | E112: 1.22 | F112: 1.22 | G112: 0.87 | H112: 0.8 | I112: 102 | J112: 60 | K112: 1.5 | L112: 2.4 | M112: 30
C113: Ensilage Luzerne-Dactyle Ressuyage (25 % MS) 1er cycle début floraison (20/06) | D113: ND | E113: ND | F113: ND | G113: ND | H113: ND | I113: ND | J113: ND | K113: ND | L113: ND | M113: 36
C114: Ensilage Luzerne-Dactyle Ressuyage (25 % MS) 2ème cycle (regain) | D114: 21 | E114: 1.23 | F114: 1.17 | G114: 0.78 | H114: 0.69 | I114: 98 | J114: 56 | K114: 1.5 | L114: 2.8 | M114: 33
C115: Ensilage Maïs Conditions normales 25 % MS | D115: 25 | E115: 1.28 | F115: 1.23 | G115: 0.9 | H115: 0.8 | I115: 44 | J115: 63 | K115: 1.3 | L115: 0.8 | M115: 1
C116: Ensilage Maïs Conditions normales 30 % MS | D116: 30 | E116: 1.28 | F116: 1.13 | G116: 0.9 | H116: 0.8 | I116: 42 | J116: 65 | K116: 1.3 | L116: 0.8 | M116: 2
C117: Ensilage Maïs Conditions normales 35 % MS | D117: 35 | E117: 1.28 | F117: 1.05 | G117: 0.91 | H117: 0.81 | I117: 42 | J117: 67 | K117: 1.3 | L117: 0.8 | M117: 3
C118: Ensilage Maïs Mauvaises conditions < 30 % MS | D118: 25 | E118: 1.5 | F118: 1.26 | G118: 0.85 | H118: 0.73 | I118: 65 | J118: 66 | K118: 1.3 | L118: 0.8 | M118: 5
C119: Ensilage Maïs Très bonnes conditions (> 35 % MS) | D119: 35 | E119: 1.36 | F119: 1 | G119: 0.96 | H119: 0.87 | I119: 50 | J119: 71 | K119: 1.3 | L119: 0.8 | M119: 4
C120: Ensilage Prairie naturelle Enrubanné (> 45 % MS) 1er cycle épaison | D120: 55 | E120: 1.56 | F120: 1.29 | G120: 0.73 | H120: 0.65 | I120: 71 | J120: 75 | K120: 1.9 | L120: 2 | M120: 15
C121: Ensilage Prairie naturelle Enrubanné (> 45 % MS) 1er cycle début épiaison | D121: 55 | E121: 1.38 | F121: 1.11 | G121: 0.82 | H121: 0.75 | I121: 86 | J121: 83 | K121: 1.9 | L121: 2.2 | M121: 14
C122: Ensilage Prairie naturelle Enrubanné (> 45 % MS) 1er cycle début floraison | D122: ND | E122: ND | F122: ND | G122: ND | H122: ND | I122: ND | J122: ND | K122: ND | L122: ND | M122: 16
C123: Ensilage Prairie naturelle Enrubanné (> 45 % MS) 2ème cycle (regain) | D123: 55 | E123: 1.51 | F123: 1.24 | G123: 0.76 | H123: 0.68 | I123: 71 | J123: 77 | K123: 1.9 | L123: 2.2 | M123: 17
...

Sheet CONCENTRE
B1: ALIM'ovins(v. 5.1)
B2: Rationnement des ovins
I4: Ration
J5: 3 Saisissez les quantités brutes distribuées ou cliquez sur "Mélange"
B6: 1 Cliquez sur les flèches pour faire votre choix | E6: CONCENTRE N°1 | N6: Valeurs des concentrés
N7: =IF(K9="","",C10) | O7: =IF(K16="","",C17) | T7: =K16/(K9+K16) -> #DIV/0!
B8: Catégorie | E8: Valeurs alimentaires / kg brut | T8: =K9/(K9+K16) -> #DIV/0!
E9: U.F.L. | F9: P.D.I.N. | G9: P.D.I.E. | H9: Pabs | I9: Caabs | S9: =IF(C8="",0,IF(K16="",1,(K9*E10)/((K9*E10)+(E17*K16)))) -> 0 | T9: =IF(C8="",0,IF(K16="",1,(K9*F10)/((K9*F10)+(F17*K16)))) -> 0
B10: Espèce | E10: =IF(C8="Mélange fermier",COUT!F23,IF(C8="","",IF($C$8="Mon concentré",VLOOKUP($C$10,NOUVEAU!R22:AA35,3),VLOOKUP($C$10,$C$42:$I$79,3)))) | F10: =IF(C8="Mélange fermier",COUT!H23,IF(C8="","",IF($C$8="Mon concentré",VLOOKUP($C$10,NOUVEAU!R22:AA35,5),VLOOKUP($C$10,$C$42:$I$79,4)))) | G10: =IF(C8="Mélange fermier",COUT!I23,IF(C8="","",IF($C$8="Mon concentré",VLOOKUP($C$10,NOUVEAU!R22:AA35,6),VLOOKUP($C$10,$C$42:$I$79,5)))) | H10: =IF(C8="Mélange fermier",COUT!J23,IF(C8="","",IF($C$8="Mon concentré",VLOOKUP($C$10,NOUVEAU!R22:AA35,7),VLOOKUP($C$10,$C$42:$I$79,6)))) | I10: =IF(C8="Mélange fermier",COUT!K23,IF(C8="","",IF($C$8="Mon concentré",VLOOKUP($C$10,NOUVEAU!R22:AA35,8),VLOOKUP($C$10,$C$42:$I$79,7)))) | S10: =IF(C15="",0,IF(K9="",1,(K16*E17)/((K16*E17)+(K9*E10)))) -> 0 | T10: =IF(C15="",0,IF(K9="",1,(K16*F17)/((K16*F17)+(K9*F10)))) -> 0
O11: UFL | Q11: PDIN
B13: 2 Cliquez sur les flèches pour faire votre choix | E13: CONCENTRE N°2 | N13: =IF(K9="","","Concentré 1")
N14: =IF(K9="","",C10)
B15: Catégorie | E15: Valeurs alimentaires / kg brut
E16: U.F.L. | F16: P.D.I.N. | G16: P.D.I.E. | H16: Pabs | I16: Caabs | N16: =IF(K16="","","Concentré 2")
B17: Espèce | E17: =IF(C15="Mélange fermier",COUT!F23,IF(C15="","",IF($C$15="Mon concentré",VLOOKUP($C$17,NOUVEAU!R22:AA45,3),VLOOKUP($C$17,$C$42:$I$79,3)))) | F17: =IF(C15="Mélange fermier",COUT!H23,IF(C15="","",IF($C$15="Mon concentré",VLOOKUP($C$17,NOUVEAU!R22:AA45,5),VLOOKUP($C$17,$C$42:$I$79,4)))) | G17: =IF(C15="Mélange fermier",COUT!I23,IF(C15="","",IF($C$15="Mon concentré",VLOOKUP($C$17,NOUVEAU!R22:AA45,6),VLOOKUP($C$17,$C$42:$I$79,5)))) | H17: =IF(C15="Mélange fermier",COUT!J23,IF(C15="","",IF($C$15="Mon concentré",VLOOKUP($C$17,NOUVEAU!R22:AA45,7),VLOOKUP($C$17,$C$42:$I$79,6)))) | I17: =IF(C15="Mélange fermier",COUT!K23,IF(C15="","",IF($C$15="Mon concentré",VLOOKUP($C$17,NOUVEAU!R22:AA45,8),VLOOKUP($C$17,$C$42:$I$79,7)))) | N17: =IF(K16="","",C17)
E22: =IF($C$8="Mélange fermier","Mélange fermier",IF($C$8="Céréale",F22,IF($C$8="Tourteau",G22,IF($C$8="Divers",K22,IF($C$8="Mon concentré",NOUVEAU!R22,I22))))) -> Pois | F22: Blé | G22: Colza 35 | I22: Pois | K22: Drêches de brasserie
C23: Céréale | E23: =IF($C$8="Mélange fermier","",IF($C$8="Céréale",F23,IF($C$8="Tourteau",G23,IF($C$8="Divers",K23,IF($C$8="Mon concentré",NOUVEAU!R23,I23))))) -> Lupin | F23: Orge | G23: Soja 48 | I23: Lupin | K23: Graines de Colza
C24: Tourteau | E24: =IF($C$8="Mélange fermier","",IF($C$8="Céréale",F24,IF($C$8="Tourteau",G24,IF($C$8="Divers",K24,IF($C$8="Mon concentré",NOUVEAU!R24,I24))))) -> Féverole | F24: Avoine | G24: Tournesol | I24: Féverole | K24: Drêches de blé
C25: Protéagineux | E25: =IF($C$8="Mélange fermier","",IF($C$8="Céréale",F25,IF($C$8="Tourteau",G25,IF($C$8="Divers",K25,IF($C$8="Mon concentré",NOUVEAU!R25,I25))))) -> Vesce | F25: Triticale | G25: Lin | I25: Vesce | K25: Huile de Colza
C26: Divers | E26: =IF($C$8="Mélange fermier","",IF($C$8="Céréale",F26,IF($C$8="Tourteau",G26,IF($C$8="Divers",K26,IF($C$8="Mon concentré",NOUVEAU!R26,I26))))) -> Soja extrudé | F26: Seigle | G26: Arachide | I26: Soja extrudé | K26: Luzerne deshydratée
C27: Mon concentré | E27: =IF($C$8="Mélange fermier","",IF($C$8="Céréale",F27,IF($C$8="Tourteau",G27,IF($C$8="Divers",K27,IF($C$8="Mon concentré",NOUVEAU!R27,I27))))) | F27: Maïs grain | G27: Coton déshuilé | K27: Mélasse
C28: Mélange fermier | E28: =IF($C$8="Mélange fermier","",IF($C$8="Céréale",F28,IF($C$8="Tourteau",G28,IF($C$8="Divers",K28,IF($C$8="Mon concentré",NOUVEAU!R28,I28))))) | F28: Sarrazin | G28: Tournesol décortiqué | K28: Lait écrémé en poudre
E29: =IF($C$8="Mélange fermier","",IF($C$8="Céréale",F29,IF($C$8="Tourteau",G29,IF($C$8="Divers",K29,IF($C$8="Mon concentré",NOUVEAU!R29,I29))))) | F29: Sorgho | G29: Soja tanné | K29: Pulpe de Betterave
E31: =IF($C$15="Mélange fermier","Mélange fermier",IF($C$15="Céréale",F31,IF($C$15="Tourteau",G31,IF($C$15="Divers",K31,IF($C$15="Mon concentré",NOUVEAU!R22,I31))))) -> Pois | F31: Blé | G31: Colza 35 | I31: Pois | K31: Drêches de brasserie
C32: Céréale | E32: =IF($C$15="Mélange fermier","",IF($C$15="Céréale",F32,IF($C$15="Tourteau",G32,IF($C$15="Divers",K32,IF($C$15="Mon concentré",NOUVEAU!R23,I32))))) -> Lupin | F32: Orge | G32: Soja 48 | I32: Lupin | K32: Graines de Colza
C33: Tourteau | E33: =IF($C$15="Mélange fermier","",IF($C$15="Céréale",F33,IF($C$15="Tourteau",G33,IF($C$15="Divers",K33,IF($C$15="Mon concentré",NOUVEAU!R24,I33))))) -> Féverole | F33: Avoine | G33: Tournesol | I33: Féverole | K33: Drêches de blé
C34: Protéagineux | E34: =IF($C$15="Mélange fermier","",IF($C$15="Céréale",F34,IF($C$15="Tourteau",G34,IF($C$15="Divers",K34,IF($C$15="Mon concentré",NOUVEAU!R25,I34))))) -> Vesce | F34: Triticale | G34: Lin | I34: Vesce | K34: Huile de Colza
C35: Divers | E35: =IF($C$15="Mélange fermier","",IF($C$15="Céréale",F35,IF($C$15="Tourteau",G35,IF($C$15="Divers",K35,IF($C$15="Mon concentré",NOUVEAU!R26,I35))))) -> Soja extrudé | F35: Seigle | G35: Arachide | I35: Soja extrudé | K35: Luzerne deshydratée
C36: Mes aliments | E36: =IF($C$15="Mélange fermier","",IF($C$15="Céréale",F36,IF($C$15="Tourteau",G36,IF($C$15="Divers",K36,IF($C$15="Mon concentré",NOUVEAU!R27,I36))))) | F36: Maïs grain | G36: Coton déshuilé | K36: Mélasse
E37: =IF($C$15="Mélange fermier","",IF($C$15="Céréale",F37,IF($C$15="Tourteau",G37,IF($C$15="Divers",K37,IF($C$15="Mon concentré",NOUVEAU!R28,I37))))) | F37: Sarrazin | G37: Tournesol décortiqué | K37: Lait écrémé en poudre
E38: =IF($C$15="Mélange fermier","",IF($C$15="Céréale",F38,IF($C$15="Tourteau",G38,IF($C$15="Divers",K38,IF($C$15="Mon concentré",NOUVEAU!R29,I38))))) | F38: Sorgho | G38: Soja tanné | K38: Pulpe de Betterave
C41: Catégorie | D41: C | E41: U.F.L. | F41: P.D.I.N. | G41: P.D.I.E. | H41: Pabs | I41: Caabs
C42: Arachide | D42: 90 | E42: 1 | F42: 347 | G42: 215 | H42: =K42*(D42/100) -> 3.69 | I42: =N42*(D42/100) -> 1.08 | K42: 4.1 | N42: 1.2
C43: Avoine | D43: 88 | E43: 0.77 | F43: 61 | G43: 61 | H43: =K43*(D43/100) -> 2.376 | I43: =N43*(D43/100) -> 0.616 | K43: 2.7 | N43: 0.7
C44: Blé | D44: 87 | E44: 1.02 | F44: 70 | G44: 89 | H44: =K44*(D44/100) -> 2.262 | I44: =N44*(D44/100) -> 0.348 | K44: 2.6 | N44: 0.4
C45: Colza 35 | D45: 89 | E45: 0.85 | F45: 219 | G45: 138 | H45: =K45*(D45/100) -> 8.188 | I45: =N45*(D45/100) -> 4.628 | K45: 9.2 | N45: 5.2
C46: Colza tanné | E46: 0.85 | F46: 255 | G46: 246 | H46: 9.2 | I46: 5.2
C47: Corn gluten | E47: 0.93 | F47: 127 | G47: 102 | H47: 6.8 | I47: 1
C48: Coton | D48: 91 | E48: 0.94 | F48: 131 | G48: 77 | H48: =K48*(D48/100) -> 4.641 | I48: =N48*(D48/100) -> 0.91 | K48: 5.1 | N48: 1
C49: Coton déshuilé | E49: 0.8 | F49: 254 | G49: 173 | H49: 7.9 | I49: 1.5
C50: Drêches de blé | E50: 0.96 | F50: 228 | G50: 143 | H50: 5.4 | I50: 2
C51: Drêches de brasserie | D51: 92 | E51: 0.76 | F51: 178 | G51: 157 | H51: =K51*(D51/100) -> 4.508 | I51: =N51*(D51/100) -> 1.196 | K51: 4.9 | N51: 1.3
C52: Féverole | D52: 86 | E52: 1.03 | F52: 170 | G52: 97 | H52: =K52*(D52/100) -> 3.526 | I52: =N52*(D52/100) -> 0.774 | K52: 4.1 | N52: 0.9
C53: Graine de Colza | D53: 92 | E53: 1.68 | F53: 12 | G53: 61 | H53: =K53*(D53/100) -> 4.876 | I53: =N53*(D53/100) -> 2.576 | K53: 5.3 | N53: 2.8
C54: Huile de colza | D54: 100 | E54: 2.73 | F54: 0 | G54: 0 | H54: =K54*(D54/100) -> 0 | I54: =N54*(D54/100) -> 0 | K54: 0 | N54: 0
C55: Lin | D55: 89 | E55: 0.88 | F55: 227 | G55: 179 | H55: =K55*(D55/100) -> 5.34 | I55: =N55*(D55/100) -> 2.492 | K55: 6 | N55: 2.8
C56: Lupin | D56: 89 | E56: 1.18 | F56: 213 | G56: 106 | H56: =K56*(D56/100) -> 2.848 | I56: =N56*(D56/100) -> 1.869 | K56: 3.2 | N56: 2.1
C57: Luzerne déhydratée | D57: 91 | E57: 0.62 | F57: 103 | G57: 91 | H57: =K57*(D57/100) -> 1.729 | I57: =N57*(D57/100) -> 5.915 | K57: 1.9 | N57: 6.5
C58: Maïs grain | D58: 86 | E58: 1.06 | F58: 64 | G58: 84 | H58: =K58*(D58/100) -> 1.892 | I58: =N58*(D58/100) -> 0.258 | K58: 2.2 | N58: 0.3
C59: Mélasse | D59: 76 | E59: 0.75 | F59: 63 | G59: 54 | H59: =K59*(D59/100) -> 0.152 | I59: =N59*(D59/100) -> 0.38 | K59: 0.2 | N59: 0.5
C60: Orge | D60: 87 | E60: 0.95 | F60: 69 | G60: 87 | H60: =K60*(D60/100) -> 2.61 | I60: =N60*(D60/100) -> 0.435 | K60: 3 | N60: 0.5
C61: Pois | D61: 86 | E61: 1.04 | F61: 130 | G61: 83 | H61: =K61*(D61/100) -> 2.924 | I61: =N61*(D61/100) -> 0.602 | K61: 3.4 | N61: 0.7
C62: Poudre de lait écrémé | D62: 95 | E62: 1.15 | F62: 196 | G62: 75 | H62: =K62*(D62/100) -> 9.215 | I62: =N62*(D62/100) -> 11.115 | K62: 9.7 | N62: 11.7
... C66: Soja 48 | D66: 88 | E66: 1.06 | F66: 331 | G66: 229 | H66: =K66*(D66/100) -> 4.4 | I66: =N66*(D66/100) -> 1.848 | K66: 5 | N66: 2.1
C67: Soja extrudé | E67: 1.27 | F67: 262 | G67: 214 | H67: 4.6 | I67: 2
C68: Soja tanné | E68: 1.06 | F68: 389 | G68: 374 | H68: 5 | I68: 2.1
C69: Son de blé | E69: 0.82 | F69: 94 | G69: 80 | H69: 8.2 | I69: 0.9
C70: Sorgho | D70: 87 | E70: 1.05 | F70: 67 | G70: 87 | H70: =K70*(D70/100) -> 2.088 | I70: =N70*(D70/100) -> 0.174 | K70: 2.4 | N70: 0.2
C71: Tournesol | D71: 89 | E71: 0.56 | F71: 178 | G71: 93 | H71: =K71*(D71/100) -> 6.586 | I71: =N71*(D71/100) -> 2.136 | K71: 7.4 | N71: 2.4
C72: Tournesol décortiqué | E72: 0.66 | F72: 219 | G72: 115 | H72: 7.8 | I72: 2.5
C73: Triticale | D73: 87 | E73: 1.01 | F73: 63 | G73: 84 | H73: =K73*(D73/100) -> 2.61 | I73: =N73*(D73/100) -> 0.435 | K73: 3 | N73: 0.5
C74: Urée | D74: 98 | E74: 0 | F74: 1443 | G74: 0 | H74: =K74*(D74/100) -> 0 | I74: =N74*(D74/100) -> 0 | K74: 0 | N74: 0
C75: Vesce | D75: 89 | E75: 1.02 | F75: 161 | G75: 90 | H75: =K75*(D75/100) -> 3.382 | I75: =N75*(D75/100) -> 0.89 | K75: 3.8 | N75: 1

Sheet CMV
B1: ALIM'ovins(v. 5.1)
B2: Rationnement des ovins
I4: Ration
B6: Choisir le C.M.V. ayant le rapport "Ca / P" le plus approchant du déficit | P6: Pabs | Q6: Caabs
C7: 1 Cliquez sur les flèches pour choisir le CMV | G7: Ca / P ration (avant correction) | L7: C.M.V. choisi | O7: 100 % des A.A.R. | U7: =ANIMAL!H16 -> 3.2 | V7: =ANIMAL!I16 -> 3.5
B8: Type | G8: =IF(L24=TRUE,"Un CMV n'est pas nécessaire",IF(L14="","",IF(L12<0.2,"Utilisez un CMV pauvre en P",CONCATENATE("Utilisez un CMV avec ",INT(1.63*(L14/L12))," fois plus de Ca que de P")))) -> Utilisez un CMV avec 1 fois plus de Ca que de P | L8: =CONCATENATE("C.M.V.",C8) -> C.M.V. | O8: Avant correction | U8: =IF(RATION!I24="",RATION!I16,RATION!I16+RATION!I24) | V8: =IF(RATION!J24="",RATION!J16,RATION!J16+RATION!J24)
T10: 0 | U10: =U8/U7 -> #VALUE! | V10: =V8/V7 -> #VALUE! | W10: 0
B11: 2 Saisir la quantité de CMV choisie ou accepter la quantité proposée | L11: Déficit Pabs | P11: =IF(L12="","",U10) -> #VALUE! | R11: =IF(L14="","",V10) -> #VALUE! | T11: 1 | U11: 1 | V11: 1 | W11: 1
D12: g. | G12: Valeurs alimentaires / kg brut | L12: =IF(ANIMAL!C8="","",IF(SUM(RATION!I24,RATION!I16)-RATION!I8>=0,0,-(SUM(RATION!I24,RATION!I16)-RATION!I8))) -> 3.2 | O12: 100 % des A.A.R.
G13: Pabs | I13: Caabs | L13: Déficit Caabs | T13: =IF(C8="",0,(C12/1000)*G14) -> 0 | U13: =T13+U8 -> #VALUE! | V13: 0 | W13: =U13/U7 -> #VALUE! | X13: =U14/V7 -> #VALUE!
B14: Ca / P | C14: =IF(C8="","",IF(VLOOKUP(C8,C20:H40,4)>10,"ns",VLOOKUP(C8,C20:H40,4))) | E14: =IF(C8="","",G42) | G14: =IF(C8="","",VLOOKUP(C8,C20:H40,5)) | I14: =IF(C8="","",VLOOKUP(C8,C20:H40,6)) | L14: =IF(ANIMAL!C8="","",IF(SUM(RATION!J24,RATION!J16)-RATION!J8>=0,0,-(SUM(RATION!J24,RATION!J16)-RATION!J8))) -> 3.5 | O14: Après correction | T14: =IF(C8="",0,(C12/1000)*I14) -> 0 | U14: =T14+V8 -> #VALUE! | V14: 1 | W14: 1 | X14: 1
C16: =IF(C8="","",IF(E14<10,"Un CMV n'est pas nécessaire - Cliquez sur Valider sans rien saisir","")) | P16: =IF(L12="","",W13) -> #VALUE! | R16: =IF(L14="","",X13) -> #VALUE!
C20: 0 - 27 | F20: =J20/I20 -> 2700 | G20: 0.1 | H20: =J20*0.4 -> 108 | I20: 0.1 | J20: 270
C21: 10 - 20 | F21: =J21/I21 -> 2 | G21: =I21*0.65 -> 65 | H21: =J21*0.4 -> 80 | I21: 100 | J21: 200
C22: 10 - 6 | F22: =J22/I22 -> 0.6 | G22: =I22*0.65 -> 65 | H22: =J22*0.4 -> 24 | I22: 100 | J22: 60
C23: 12 - 12 | F23: =J23/I23 -> 1 | G23: =I23*0.65 -> 78 | H23: =J23*0.4 -> 48 | I23: 120 | J23: 120
C24: 2 - 28 | F24: =J24/I24 -> 14 | G24: =I24*0.65 -> 13 | H24: =J24*0.4 -> 112 | I24: 20 | J24: 280 | L24: =AND(L12<0.2,L14<0.2) -> FALSE
C25: 3 - 27 | F25: =J25/I25 -> 9 | G25: =I25*0.65 -> 19.5 | H25: =J25*0.4 -> 108 | I25: 30 | J25: 270
C26: 4 - 21 | F26: =J26/I26 -> 5.25 | G26: =I26*0.65 -> 26 | H26: =J26*0.4 -> 84 | I26: 40 | J26: 210
C27: 5 - 20 | F27: =J27/I27 -> 4 | G27: =I27*0.65 -> 32.5 | H27: =J27*0.4 -> 80 | I27: 50 | J27: 200
C28: 5 - 22 | F28: =J28/I28 -> 4.4 | G28: =I28*0.65 -> 32.5 | H28: =J28*0.4 -> 88 | I28: 50 | J28: 220
C29: 5 - 25 | F29: =J29/I29 -> 5 | G29: =I29*0.65 -> 32.5 | H29: =J29*0.4 -> 100 | I29: 50 | J29: 250
C30: 6 - 18 | F30: =J30/I30 -> 3 | G30: =I30*0.65 -> 39 | H30: =J30*0.4 -> 72 | I30: 60 | J30: 180
C31: 6 - 6 | F31: =J31/I31 -> 1 | G31: =I31*0.65 -> 39 | H31: =J31*0.4 -> 24 | I31: 60 | J31: 60
C32: 7 - 21 | F32: =J32/I32 -> 3 | G32: =I32*0.65 -> 45.5 | H32: =J32*0.4 -> 84 | I32: 70 | J32: 210
C33: 7 - 23 | F33: =J33/I33 -> 3.2857143 | G33: =I33*0.65 -> 45.5 | H33: =J33*0.4 -> 92 | I33: 70 | J33: 230
C34: 8 - 12 | F34: =J34/I34 -> 1.5 | G34: =I34*0.65 -> 52 | H34: =J34*0.4 -> 48 | I34: 80 | J34: 120
C35: 8 - 16 | F35: =J35/I35 -> 2 | G35: =I35*0.65 -> 52 | H35: =J35*0.4 -> 64 | I35: 80 | J35: 160
C36: 8 - 18 | F36: =J36/I36 -> 2.25 | G36: =I36*0.65 -> 52 | H36: =J36*0.4 -> 72 | I36: 80 | J36: 180
... C40: CaCO3 | F40: =J40/I40 -> #DIV/0! | G40: =I40*0.65 -> 0 | H40: =J40*0.4 -> 160 | I40: 0 | J40: 400
E42: =IF(L14=0,ABS(L12)/((G14+1.01)/1000),ABS(L14)/(I14/1000)) -> #VALUE! | G42: =ROUND(E42/5,0)*5 -> #VALUE!

Sheet BILAN
B1: ALIM'ovins(v. 5.1)
B2: Rationnement des ovins
I4: Bilan alimentaire
C7: Saisir l'effectif d'animaux du lot | J7: =ANIMAL!E11 -> Brebis 70 kg Gestante Double Semaines - 3 à - 4 | N7: Cout de concentré (€ / animal / jour)
C10: Saisir la durée d'alimentation (en jours) | P10: =IF(G7="","",(M32/G7)/G10)
C14: QUANTITE DE FOURRAGE | P14: Pour 1 tonne de ration complète
C15: =IF(FOURRAGE!C9="","",FOURRAGE!E9) | K15: =IF(C15="","",(G7*G10*FOURRAGE!L10)/1000) | M15: tonnes (brut) | Q15: =IF(K15="","",IF(K15=0,0,K15/(SUM($K$15,$K$18,$H$26,$H$28,$H$30))*1000)) | R15: kg
C18: =IF(FOURRAGE!C23="","",FOURRAGE!E23) | K18: =IF(C18="","",(G7*G10*FOURRAGE!L24)/1000) | M18: tonnes (brut) | Q18: =IF(K18="","",IF(K18=0,0,K18/(SUM($K$15,$K$18,$H$26,$H$28,$H$30))*1000)) | R18: kg
Q21: Pourcentage de concentré
C23: COUT DE CONCENTRE | G23: kg / jour | H23: Besoins pour la période | K23: Coût | M23: Cout total | Q23: =SUM(Q26,Q28,Q30)/1000 -> 0
K24: unitaire
C26: =IF(CONCENTRE!C10="","",CONCENTRE!C10) | G26: =IF(CONCENTRE!K9="","",CONCENTRE!K9) | H26: =IF(G26="","",(G26*$G$10*$G$7)/1000) | I26: tonnes | L26: / t | M26: =IF(G26="","",K26*H26) | Q26: =IF(K26=0,0,IF(M26="",0,H26/(SUM($K$15,$K$18,$H$26,$H$28,$H$30))*1000)) -> 0 | R26: kg
C28: =IF(CONCENTRE!C17="","",CONCENTRE!C17) | G28: =IF(CONCENTRE!K16="","",CONCENTRE!K16) | H28: =IF(G28="","",(G28*$G$10*$G$7)/1000) | I28: tonnes | L28: / t | M28: =IF(G28="","",K28*H28) | Q28: =IF(K28=0,0,IF(M28="",0,H28/(SUM($K$15,$K$18,$H$26,$H$28,$H$30))*1000)) -> 0 | R28: kg
C30: =IF(CMV!C8="","",CMV!C8) | G30: =IF(CMV!C12="","",CMV!C12/1000) | H30: =IF(G30="","",(G30*$G$10*$G$7)/1000) | I30: tonnes | L30: / t | M30: =IF(G30="","",K30*H30) | Q30: =IF(K30=0,0,IF(M30="",0,H30/(SUM($K$15,$K$18,$H$26,$H$28,$H$30))*1000)) -> 0 | R30: kg
C32: COUT TOTAL DE CONCENTRE (en € pour le lot et pour la période) | M32: =IF($G$7="","",SUM(M26,M28,M30)) | Q32: =SUM(Q30,Q28,Q26,Q18,Q15) -> 0 | R32: kg
E37: =Q15
B40: 1 | C40: Janvier | D40: 2010
B41: 2 | C41: Février | D41: 2011
B42: 3 | C42: Mars | D42: 2012
B43: 4 | C43: Avril | D43: 2013
B44: 5 | C44: Mai | D44: 2014
B45: 6 | C45: Juin | D45: 2015
B46: 7 | C46: Juillet | D46: 2016
B47: 8 | C47: Août
B48: 9 | C48: Septembre
B49: 10 | C49: Octobre
B50: 11 | C50: Novembre
B51: 12 | C51: Décembre
B52: 13
B53: 14
B54: 15
B55: 16
B56: 17
B57: 18
B58: 19
B59: 20
B60: 21
B61: 22
B62: 23
B63: 24
... B70: 31

Sheet MELANGE
B1: ALIM'ovins(v. 5.0)
B2: Rationnement des bovins allaitants
B5: CALCUL DE LA COMPOSITION D'UN MELANGE DE 2 CONCENTRES
B6: Système de 2 équations et 2 inconnues (x et y)
B8: =IF(E9="","1 Mélange n'est pas nécessaire !",IF(H9<0,"1 Mélange n'est pas nécessaire ! Cliquez sur Retour","")) -> 1 Mélange n'est pas nécessaire ! | E8: =IF(CONCENTRE!C10="","",CONCENTRE!C10) | F8: x | G8: + | H8: =IF(CONCENTRE!C17="","",CONCENTRE!C17) | I8: y
E9: =E24 | F9: kg | H9: =H24 | I9: kg
C11: Déficit | E11: =IF(E9="","",E20/(E20+H20)) | H11: =IF(H9="","",H20/(E20+H20))
B12: UFL | C12: =IF(CONCENTRE!E10="","",-RATION!F18) | D12: = | E12: =IF(CONCENTRE!C10="",0.001,CONCENTRE!E10) -> 0.001 | F12: x | G12: + | H12: =IF(CONCENTRE!C17="",0.001,CONCENTRE!E17) -> 0.001 | I12: y
B14: PDIN | C14: =IF(CONCENTRE!F10="","",-RATION!G18) | D14: = | E14: =IF(CONCENTRE!C10="",0.001,CONCENTRE!F10) -> 0.001 | F14: x | G14: + | H14: =IF(CONCENTRE!C17="",0.001,CONCENTRE!F17) -> 0.001 | I14: y
B16: =IF(E9="","VERIFIER vos concentrés, le mélange n'est pas adapté !",IF(H9="","VERIFIER vos concentrés, le mélange n'est pas adapté !","")) -> VERIFIER vos concentrés, le mélange n'est pas adapté !
E20: =IF((C12-(H12*H20))/E12<0,"",IF(E12=0.001,0,IF(C12<=0.1,0,IF(C12="","",ROUND((C12-(H12*H20))/E12,1))))) -> #VALUE! | H20: =IF((C14-(C12*E14)/E12)/(H14-((H12*E14)/E12))<0,0,IF(H12=0.001,0,IF(C14<=0.1,0,IF(C12="","",ROUND((C14-(C12*E14)/E12)/(H14-((H12*E14)/E12)),1))))) -> #VALUE!
E22: =IF(E12=0.001,0,IF(C12<=0.1,0,IF(C12="","",(C12-(H12*H20))/E12))) -> 0 | H22: =IF(H12=0.001,0,IF(C14<=0.1,0,IF(C12="","",(C14-(C12*E14)/E12)/(H14-((H12*E14)/E12))))) -> 0
E24: =IF(E22<=0,"",IF(H22>0,ROUND(E22,1),ROUND(C12/E12,1))) | H24: =IF(H22<=0,"",IF(E22>0,ROUND(H20,1),ROUND(C12/H12,1)))
C27: (C14-(C12*E14)/E12)/(H14-((H12*E14)/E12))))
C28: (C12-(H12*H9))/E12)
C30: SI(E12=0,001;0;SI(C12<=0,1;0;SI(C12="";"";(C12-(H12*H9))/E12)))
C31: SI(H12=0,001;0;SI(C14<=0,1;0;SI(C12="";"";(C14-(C12*E14)/E12)/(H14-((H12*E14)/E12)))))

Sheet RATION
B1: ALIM'ovins(v. 5.1)
B2: Rationnement des ovins
F4: Ration
B6: Catégorie | E6: Apports Alimentaires Recommandés | L6: REPARTITION DES APPORTS | T6: UFL | U6: PDIN | V6: PDIE | W6: P | X6: Ca
E7: UEM | F7: UFL | G7: PDIN | H7: PDIE | I7: Pabs | J7: Caabs | L7: en % des besoins alimentaires | T7: =F29/F8 -> #VALUE! | U7: =G29/G8 -> #VALUE! | V7: =H29/H8 -> #VALUE! | W7: =I29/I8 -> #VALUE! | X7: =J29/J8 -> #VALUE!
B8: =IF(ANIMAL!E11="","",ANIMAL!E11) -> Brebis 70 kg Gestante Double Semaines - 3 à - 4 | E8: =IF($B$8="","",ANIMAL!E16) -> 1.71 | F8: =IF($B$8="","",ANIMAL!F16) -> 1.14 | G8: =IF($B$8="","",ANIMAL!G16) -> 146 | H8: =IF($B$8="","",ANIMAL!G16) -> 146 | I8: =IF($B$8="","",ANIMAL!H16) -> 3.2 | J8: =IF($B$8="","",ANIMAL!I16) -> 3.5 | T8: 1 | U8: 1 | V8: 1 | W8: 1 | X8: 1
B10: Quantité kg | C10: Aliments (valeurs / kg MS) | D10: Valeurs alimentaires
D11: MS | E11: UEM | F11: UFL | G11: PDIN | H11: PDIE | I11: Pabs | J11: Caabs
B12: =IF(FOURRAGE!L10="","",FOURRAGE!L10) | C12: =FOURRAGE!E9 | D12: =FOURRAGE!E15 | E12: =FOURRAGE!F15 | F12: =FOURRAGE!G15 | G12: =FOURRAGE!H15 | H12: =FOURRAGE!I15 | I12: =FOURRAGE!J15 | J12: =FOURRAGE!L15
D13: =IF(B12="","",B12*(D12/100)) | E13: =IF($D$13="","",$D$13*E12) | F13: =IF($D$13="","",$D$13*F12) | G13: =IF($D$13="","",$D$13*G12) | H13: =IF($D$13="","",$D$13*H12) | I13: =IF($D$13="","",$D$13*I12) | J13: =IF($D$13="","",$D$13*J12) | M13: =F29/F8 -> #VALUE! | N13: =G29/G8 -> #VALUE! | P13: =H29/H8 -> #VALUE! | Q13: =I29/I8 -> #VALUE! | R13: =J29/J8 -> #VALUE!
B14: =IF(FOURRAGE!L24="","",FOURRAGE!L24) | C14: =FOURRAGE!E23 | D14: =IF(C14="","",FOURRAGE!E29) | E14: =IF(C14="","",FOURRAGE!F29) | F14: =IF(C14="","",FOURRAGE!G29) | G14: =IF(C14="","",FOURRAGE!H29) | H14: =IF(C14="","",FOURRAGE!I29) | I14: =IF(C14="","",FOURRAGE!J29) | J14: =IF(C14="","",FOURRAGE!L29) | L14: Part des fourrages et des concentrés dans la ration | O14: MS | Q14: UFL | R14: PDIN
D15: =IF(B14="","",B14*(D14/100)) | E15: =IF($D$15="","",$D$15*E14) | F15: =IF($D$15="","",$D$15*F14) | G15: =IF($D$15="","",$D$15*G14) | H15: =IF($D$15="","",$D$15*H14) | I15: =IF($D$15="","",$D$15*I14) | J15: =IF($D$15="","",$D$15*J14)
B16: =IF(SUM(B12,B14)=0,"",SUM(B12,B14)) | C16: Ration de base | D16: =IF(B16="","",SUM(D13,D15)) | E16: =IF(B16="","",SUM(E13,E15)) | F16: =IF(B16="","",SUM(F13,F15)) | G16: =IF(B16="","",SUM(G13,G15)) | H16: =IF(B16="","",SUM(H13,H15)) | I16: =IF(B16="","",SUM(I13,I15)) | J16: =IF(B16="","",SUM(J13,J15)) | L16: Concentrés
O17: =IF(G7="","",IF(V18=0,"",V18))
B18: Différence | E18: =IF(E8="","",E16-E8) -> #VALUE! | F18: =IF(F8="","",F16-F8) -> #VALUE! | G18: =IF(G8="","",G16-G8) -> #VALUE! | H18: =IF(H8="","",H16-H8) -> #VALUE! | I18: =IF(I8="","",I16-I8) -> #VALUE! | J18: =IF(J8="","",J16-J8) -> #VALUE! | T18: Fourrage 1 | U18: =B12 | V18: =SUM(U18,U19)/SUM(U18,U19,U20,U21,0.0001) -> 0 | W18: =F13 | X18: =SUM(W18,W19)/SUM(W18,W19,W20,W21,0.0001) -> 0 | Y18: =G13 | Z18: =SUM(Y18,Y19)/SUM(Y18,Y19,Y20,Y21,0.0001) -> 0
L19: Fourrages | O19: =IF(V19=0,"",V19) | T19: Fourrage 2 | U19: =B14 | V19: =SUM(U20,U21)/SUM(U18,U19,U20,U21,0.0001) -> 0 | W19: =F15 | X19: =SUM(W20,W21)/SUM(W18,W19,W20,W21,0.0001) -> 0 | Y19: =H15 | Z19: =SUM(Y20,Y21)/SUM(Y18,Y19,Y20,Y21,0.0001) -> 0
B20: =IF(CONCENTRE!K9="","",CONCENTRE!K9) | C20: =IF(B20="","",CONCENTRE!C10) | F20: =IF(C20="","",CONCENTRE!E10) | G20: =IF(C20="","",CONCENTRE!F10) | H20: =IF(C20="","",CONCENTRE!G10) | I20: =IF(C20="","",CONCENTRE!H10) | J20: =IF(C20="","",CONCENTRE!I10) | T20: Concentré 1 | U20: =B20 | W20: =F21 | Y20: =G21
F21: =IF(B20="","",$B$20*F20) | G21: =IF(B20="","",$B$20*G20) | H21: =IF(B20="","",$B$20*H20) | I21: =IF(B20="","",$B$20*I20) | J21: =IF(B20="","",$B$20*J20) | T21: Concentré 2 | U21: =B22 | W21: =F23 | Y21: =G23
B22: =IF(CONCENTRE!K16="","",CONCENTRE!K16) | C22: =IF(B22="","",CONCENTRE!C17) | F22: =IF(C22="","",CONCENTRE!E17) | G22: =IF(C22="","",CONCENTRE!F17) | H22: =IF(C22="","",CONCENTRE!G17) | I22: =IF(C22="","",CONCENTRE!H17) | J22: =IF(C22="","",CONCENTRE!I17)
F23: =IF(B22="","",$B$22*F22) | G23: =IF(B22="","",$B$22*G22) | H23: =IF(B22="","",$B$22*H22) | I23: =IF(B22="","",$B$22*I22) | J23: =IF(B22="","",$B$22*J22) | L23: REPARTITION DES ALIMENTS
B24: =IF(SUM(B20,B22)=0,"",SUM(B20,B22)) | C24: Concentrés | F24: =IF(B24="","",SUM(F21,F23)) | G24: =IF(B24="","",SUM(G21,G23)) | H24: =IF(B24="","",SUM(H21,H23)) | I24: =IF(B24="","",SUM(I21,I23)) | J24: =IF(B24="","",SUM(J21,J23))
B26: RMIC = | C26: PDIN - PDIE | D26: =IF(D29="","",(G29-H29)/F29) | E26: * | F26: =IF(CMV!C8="","",(CMV!C12)/1000) | G26: =IF(F26="","",CMV!L8) | I26: =CMV!G14 | J26: =CMV!I14
C27: UFL | I27: =IF(F26="","",I26*F26) | J27: =IF(F26="","",J26*F26)
B29: =IF(B16="","",SUM(B16,B24,F26)) | C29: TOTAL RATION | D29: =D16 | E29: =E16 | F29: =IF(F18="","",SUM(F24,F16)) -> #VALUE! | G29: =IF(G18="","",SUM(G24,G16)) -> #VALUE! | H29: =IF(H18="","",SUM(H24,H16)) -> #VALUE! | I29: =IF(I18="","",SUM(I24,I16,I27)) -> #VALUE! | J29: =IF(J18="","",SUM(J24,J16,J27)) -> #VALUE!
C31: Différence | E31: =IF(B16="","",E29-E8) | F31: =IF($B$16="","",F29-F8) | G31: =IF($B$16="","",G29-G8) | H31: =IF($B$16="","",H29-H8) | I31: =IF($B$16="","",I29-I8) | J31: =IF($B$16="","",J29-J8)
A32: * RMIC < - 12 (Brebis allaitantes - agneaux simples) RMIC < - 6 (Brebis allaitantes - agneaux doubles) | E32: =IF(E31="","",IF(E31>0.01,"ATTENTION ! La capacité d'ingestion est dépassée: REDUISEZ LES QUANTITES DE FOURRAGE",""))

Sheet COUT
B1: ALIM'ovins(v. 5.1)
B2: Rationnement des ovins
F4: Formulation d'aliment et coût
B5: FORMULATION ET CALCUL DU COUT D'UN MELANGE FERMIER | P5: Répartition des matières premières
B6: Cliquez dans la case "Matières premières" et choisissez dans la liste - Saisissez ensuite les quantités introduites dans le mélange | O6: Coût des matières premières (€ /tonne)
B7: Quantités kg | C7: Matières premières | E7: Valeurs alimentaires
E8: % | F8: UFL | G8: UFV | H8: PDIN | I8: PDIE | J8: Pabs | K8: Caabs | L8: MAT | M8: CB
E9: =IF(B9="","",B9/$B$23) | F9: =IF(B9="","",IF(C9="Mes_concentrés",VLOOKUP(D9,NOUVEAU!$R$22:$AA$38,3),VLOOKUP($D9,$D29:$K76,3))) | G9: =IF(B9="","",IF(C9="Mes_concentrés",VLOOKUP(D9,NOUVEAU!$R$22:$AA$38,4),VLOOKUP($D9,$D29:$K76,4))) | H9: =IF(B9="","",IF(C9="Mes_concentrés",VLOOKUP(D9,NOUVEAU!$R$22:$AA$38,5),VLOOKUP($D9,$D29:$K76,5))) | I9: =IF(B9="","",IF(C9="Mes_concentrés",VLOOKUP(D9,NOUVEAU!$R$22:$AA$38,6),VLOOKUP($D9,$D29:$K76,6))) | J9: =IF(B9="","",IF(C9="Mes_concentrés",VLOOKUP(D9,NOUVEAU!$R$22:$AA$38,7),VLOOKUP($D9,$D29:$K76,7))) | K9: =IF(B9="","",IF(C9="Mes_concentrés",VLOOKUP(D9,NOUVEAU!$R$22:$AA$38,8),VLOOKUP($D9,$D29:$K76,8))) | L9: =IF(B9="","",IF(C9="Mes_concentrés",VLOOKUP(D9,NOUVEAU!$R$22:$AC$38,9),VLOOKUP($D9,$D29:$M76,9))) | M9: =IF(B9="","",IF(C9="Mes_concentrés",VLOOKUP(D9,NOUVEAU!$R$22:$AC$38,10),VLOOKUP($D9,$D29:$M76,10)))
F10: =IF(B9="","",$E$9*F9) | G10: =IF(B9="","",$E$9*G9) | H10: =IF(B9="","",$E$9*H9) | I10: =IF(B9="","",$E$9*I9) | J10: =IF(B9="","",$E$9*J9) | K10: =IF(B9="","",$E$9*K9) | L10: =IF(B9="","",$E$9*L9) | M10: =IF(B9="","",$E$9*M9)
E11: =IF(B9="","",B11/$B$23) | F11: =IF(B11="","",IF(C11="Mes_concentrés",VLOOKUP(D11,NOUVEAU!$R$22:$AA$38,3),VLOOKUP($D11,$D29:$K76,3))) | G11: =IF(B11="","",IF(C11="Mes_concentrés",VLOOKUP(D11,NOUVEAU!$R$22:$AA$38,4),VLOOKUP($D11,$D29:$K76,4))) | H11: =IF(B11="","",IF(C11="Mes_concentrés",VLOOKUP(D11,NOUVEAU!$R$22:$AA$38,5),VLOOKUP($D11,$D29:$K76,5))) | I11: =IF(B11="","",IF(C11="Mes_concentrés",VLOOKUP(D11,NOUVEAU!$R$22:$AA$38,6),VLOOKUP($D11,$D29:$K76,6))) | J11: =IF(B11="","",IF(C11="Mes_concentrés",VLOOKUP(D11,NOUVEAU!$R$22:$AA$38,7),VLOOKUP($D11,$D29:$K76,7))) | K11: =IF(B11="","",IF(C11="Mes_concentrés",VLOOKUP(D11,NOUVEAU!$R$22:$AA$38,8),VLOOKUP($D11,$D29:$K76,8))) | L11: =IF(B11="","",IF(C11="Mes_concentrés",VLOOKUP(D11,NOUVEAU!$R$22:$AC$38,9),VLOOKUP($D11,$D29:$M76,9))) | M11: =IF(B11="","",IF(C11="Mes_concentrés",VLOOKUP(D11,NOUVEAU!$R$22:$AC$38,10),VLOOKUP($D11,$D29:$M76,10)))
F12: =IF(B11="","",E11*F11) | G12: =IF(B11="","",E11*G11) | H12: =IF(B11="","",E11*H11) | I12: =IF(B11="","",E11*I11) | J12: =IF(B11="","",E11*J11) | K12: =IF(B11="","",E11*K11) | L12: =IF(B11="","",E11*L11) | M12: =IF(B11="","",$E$11*M11)
E13: =IF(B9="","",B13/$B$23) | F13: =IF(B13="","",IF(C13="Mes_concentrés",VLOOKUP(D13,NOUVEAU!$R$22:$AA$38,3),VLOOKUP($D13,$D29:$K76,3))) | G13: =IF(B13="","",IF(C13="Mes_concentrés",VLOOKUP(D13,NOUVEAU!$R$22:$AA$38,4),VLOOKUP($D13,$D29:$K76,4))) | H13: =IF(B13="","",IF(C13="Mes_concentrés",VLOOKUP(D13,NOUVEAU!$R$22:$AA$38,5),VLOOKUP($D13,$D29:$K76,5))) | I13: =IF(B13="","",IF(C13="Mes_concentrés",VLOOKUP(D13,NOUVEAU!$R$22:$AA$38,6),VLOOKUP($D13,$D29:$K76,6))) | J13: =IF(B13="","",IF(C13="Mes_concentrés",VLOOKUP(D13,NOUVEAU!$R$22:$AA$38,7),VLOOKUP($D13,$D29:$K76,7))) | K13: =IF(B13="","",IF(C13="Mes_concentrés",VLOOKUP(D13,NOUVEAU!$R$22:$AA$38,8),VLOOKUP($D13,$D29:$K76,8))) | L13: =IF(B13="","",IF(C13="Mes_concentrés",VLOOKUP(D13,NOUVEAU!$R$22:$AC$38,9),VLOOKUP($D13,$D29:$M76,9))) | M13: =IF(B13="","",IF(C13="Mes_concentrés",VLOOKUP(D13,NOUVEAU!$R$22:$AC$38,10),VLOOKUP($D13,$D29:$M76,10)))
F14: =IF(B13="","",E13*F13) | G14: =IF(C13="","",E13*G13) | H14: =IF(B13="","",E13*H13) | I14: =IF(B13="","",E13*I13) | J14: =IF(B13="","",E13*J13) | K14: =IF(B13="","",E13*K13) | L14: =IF(B13="","",E13*L13) | M14: =IF(B13="","",$E$13*M13)
E15: =IF(B9="","",B15/$B$23) | F15: =IF(B15="","",IF(C15="Mes_concentrés",VLOOKUP(D15,NOUVEAU!$R$22:$AA$38,3),VLOOKUP($D15,$D29:$K76,3))) | G15: =IF(B15="","",IF(C15="Mes_concentrés",VLOOKUP(D15,NOUVEAU!$R$22:$AA$38,4),VLOOKUP($D15,$D29:$K76,4))) | H15: =IF(B15="","",IF(C15="Mes_concentrés",VLOOKUP(D15,NOUVEAU!$R$22:$AA$38,5),VLOOKUP($D15,$D29:$K76,5))) | I15: =IF(B15="","",IF(C15="Mes_concentrés",VLOOKUP(D15,NOUVEAU!$R$22:$AA$38,6),VLOOKUP($D15,$D29:$K76,6))) | J15: =IF(B15="","",IF(C15="Mes_concentrés",VLOOKUP(D15,NOUVEAU!$R$22:$AA$38,7),VLOOKUP($D15,$D29:$K76,7))) | K15: =IF(B15="","",IF(C15="Mes_concentrés",VLOOKUP(D15,NOUVEAU!$R$22:$AA$38,8),VLOOKUP($D15,$D29:$K76,8))) | L15: =IF(B15="","",IF(C15="Mes_concentrés",VLOOKUP(D15,NOUVEAU!$R$22:$AC$38,9),VLOOKUP($D15,$D29:$M76,9))) | M15: =IF(B15="","",IF(C15="Mes_concentrés",VLOOKUP(D15,NOUVEAU!$R$22:$AC$38,10),VLOOKUP($D15,$D29:$M76,10)))
F16: =IF(B15="","",E15*F15) | G16: =IF(B15="","",E15*G15) | H16: =IF(B15="","",E15*H15) | I16: =IF(B15="","",E15*I15) | J16: =IF(B15="","",E15*J15) | K16: =IF(B15="","",E15*K15) | L16: =IF(B15="","",E15*L15) | M16: =IF(B15="","",$E$15*M15)
E17: =IF(B9="","",B17/$B$23) | F17: =IF(B17="","",IF(C17="Mes_concentrés",VLOOKUP(D17,NOUVEAU!$R$22:$AA$38,3),VLOOKUP($D17,$D29:$K76,3))) | G17: =IF(B17="","",IF(C17="Mes_concentrés",VLOOKUP(D17,NOUVEAU!$R$22:$AA$38,4),VLOOKUP($D17,$D29:$K76,4))) | H17: =IF(B17="","",IF(C17="Mes_concentrés",VLOOKUP(D17,NOUVEAU!$R$22:$AA$38,5),VLOOKUP($D17,$D29:$K76,5))) | I17: =IF(B17="","",IF(C17="Mes_concentrés",VLOOKUP(D17,NOUVEAU!$R$22:$AA$38,6),VLOOKUP($D17,$D29:$K76,6))) | J17: =IF(B17="","",IF(C17="Mes_concentrés",VLOOKUP(D17,NOUVEAU!$R$22:$AA$38,7),VLOOKUP($D17,$D29:$K76,7))) | K17: =IF(B17="","",IF(C17="Mes_concentrés",VLOOKUP(D17,NOUVEAU!$R$22:$AA$38,8),VLOOKUP($D17,$D29:$K76,8))) | L17: =IF(B17="","",IF(C17="Mes_concentrés",VLOOKUP(D17,NOUVEAU!$R$22:$AC$38,9),VLOOKUP($D17,$D29:$M76,9))) | M17: =IF(B17="","",IF(C17="Mes_concentrés",VLOOKUP(D17,NOUVEAU!$R$22:$AC$38,10),VLOOKUP($D17,$D29:$M76,10)))
F18: =IF(B17="","",E17*F17) | G18: =IF(B17="","",E17*G17) | H18: =IF(B17="","",E17*H17) | I18: =IF(B17="","",E17*I17) | J18: =IF(B17="","",E17*J17) | K18: =IF(B17="","",E17*K17) | L18: =IF(B17="","",E17*L17) | M18: =IF(B17="","",$E$17*M17)
E19: =IF(B9="","",B19/$B$23) | F19: =IF(B19="","",IF(C19="Mes_concentrés",VLOOKUP(D19,NOUVEAU!$R$22:$AA$38,3),VLOOKUP($D19,$D29:$K76,3))) | G19: =IF(B19="","",IF(C19="Mes_concentrés",VLOOKUP(D19,NOUVEAU!$R$22:$AA$38,4),VLOOKUP($D19,$D29:$K76,4))) | H19: =IF(B19="","",IF(C19="Mes_concentrés",VLOOKUP(D19,NOUVEAU!$R$22:$AA$38,5),VLOOKUP($D19,$D29:$K76,5))) | I19: =IF(B19="","",IF(C19="Mes_concentrés",VLOOKUP(D19,NOUVEAU!$R$22:$AA$38,6),VLOOKUP($D19,$D29:$K76,6))) | J19: =IF(B19="","",IF(C19="Mes_concentrés",VLOOKUP(D19,NOUVEAU!$R$22:$AA$38,7),VLOOKUP($D19,$D29:$K76,7))) | K19: =IF(B19="","",IF(C19="Mes_concentrés",VLOOKUP(D19,NOUVEAU!$R$22:$AA$38,8),VLOOKUP($D19,$D29:$K76,8))) | L19: =IF(B19="","",IF(C19="Mes_concentrés",VLOOKUP(D19,NOUVEAU!$R$22:$AC$38,9),VLOOKUP($D19,$D29:$M76,9))) | M19: =IF(B19="","",IF(C19="Mes_concentrés",VLOOKUP(D19,NOUVEAU!$R$22:$AC$38,10),VLOOKUP($D19,$D29:$M76,10)))
F20: =IF(B19="","",E19*F19) | G20: =IF(B19="","",E19*G19) | H20: =IF(B19="","",E19*H19) | I20: =IF(B19="","",E19*I19) | J20: =IF(B19="","",E19*J19) | K20: =IF(B19="","",E19*K19) | L20: =IF(B19="","",E19*L19) | M20: =IF(B19="","",$E$19*M19)
F21: =CONCATENATE(ROUND(H23/F23,0)," PDI / UFL") -> #VALUE! | J21: =CONCATENATE("Ca / P = ",ROUND(K23/J23,1)) -> #VALUE!
O22: COUT € / kg
B23: =SUM(B9:B20) -> 0 | C23: kg | D23: Mon aliment | E23: =IF(B9="","",SUM(E9:E20)) | F23: =IF(F10="","",SUM(F10,F12,F14,F16,F18,F20)) | G23: =IF(G10="","",SUM(G10,G12,G14,G16,G18,G20)) | H23: =IF(H10="","",SUM(H10,H12,H14,H16,H18,H20)) | I23: =IF(I10="","",SUM(I10,I12,I14,I16,I18,I20)) | J23: =IF(J10="","",SUM(J10,J12,J14,J16,J18,J20)) | K23: =IF(K10="","",SUM(K10,K12,K14,K16,K18,K20)) | L23: =IF(L10="","",SUM(L10,L12,L14,L16,L18,L20)) | M23: =IF(M10="","",SUM(M10,M12,M14,M16,M18,M20)) | O23: =IF(B9="","",((O10*B9)+(O12*B11)+(O14*B13)+(O16*B15)+(O18*B17)+(O20*B19))/(B23*1000))
D24: Les valeurs alimentaires sont reportées dans la liste des aliments "Mon aliment"
D28: Catégorie | E28: C | F28: U.F.L. | G28: U.F.V. | H28: P.D.I.N. | I28: P.D.I.E. | J28: Pabs | K28: Caabs | L28: MAT | M28: CB
D29: Avoine | F29: 0.77 | G29: 0.71 | H29: 61 | I29: 61 | J29: 2.7 | K29: 0.7 | L29: 11.1 | M29: 13.8 | Q29: Avoine
D30: Bicarbonate de Na | F30: 0 | G30: 0 | H30: 0 | I30: 0 | J30: 0 | K30: 0 | L30: 0 | M30: 0 | Q30: Blé
B31: Céréale | D31: Blé | F31: 1.02 | G31: 1.02 | H31: 70 | I31: 89 | J31: 2.6 | K31: 0.4 | L31: 12.1 | M31: 2.6 | Q31: Maïs grain
B32: Tourteau | D32: Carbonate de Ca | F32: 0 | G32: 0 | H32: 0 | I32: 0 | J32: 0 | K32: 150 | L32: 0 | M32: 0 | Q32: Orge
B33: Graines | D33: CMV 0 - 27 | F33: 0 | G33: 0 | H33: 0 | I33: 0 | J33: 0 | K33: 108 | L33: 0 | M33: 0 | Q33: Sarrazin
B34: Divers | D34: CMV 10 - 20 | F34: 0 | G34: 0 | H34: 0 | I34: 0 | J34: 65 | K34: 80 | L34: 0 | M34: 0 | Q34: Seigle
B35: Minéraux | D35: CMV 10 - 6 | F35: 0 | G35: 0 | H35: 0 | I35: 0 | J35: 65 | K35: 24 | L35: 0 | M35: 0 | Q35: Sorgho
B36: Mes_concentrés | D36: CMV 12 - 12 | F36: 0 | G36: 0 | H36: 0 | I36: 0 | J36: 78 | K36: 48 | L36: 0 | M36: 0 | Q36: Triticale
B37: Fibres | D37: CMV 12 - 12 | F37: 0 | G37: 0 | H37: 0 | I37: 0 | J37: 78 | K37: 48 | L37: 0 | M37: 0
D38: CMV 2 - 28 | F38: 0 | G38: 0 | H38: 0 | I38: 0 | J38: 13 | K38: 112 | L38: 0 | M38: 0 | Q38: Tourteau d'arachide
D39: CMV 3 - 27 | F39: 0 | G39: 0 | H39: 0 | I39: 0 | J39: 20 | K39: 108 | L39: 0 | M39: 0 | Q39: Tourteau de colza
D40: CMV 4 - 21 | F40: 0 | G40: 0 | H40: 0 | I40: 0 | J40: 26 | K40: 84 | L40: 0 | M40: 0 | Q40: Tourteau de coton
D41: CMV 5 - 20 | F41: 0 | G41: 0 | H41: 0 | I41: 0 | J41: 32 | K41: 80 | L41: 0 | M41: 0 | Q41: Tourteau de lin
D42: CMV 5 - 25 | F42: 0 | G42: 0 | H42: 0 | I42: 0 | J42: 32 | K42: 100 | L42: 0 | M42: 0 | Q42: Tourteau de soja
D43: CMV 6 - 6 | F43: 0 | G43: 0 | H43: 0 | I43: 0 | J43: 39 | K43: 24 | L43: 0 | M43: 0 | Q43: Tourteau de tournesol
D44: CMV 7 - 21 | F44: 0 | G44: 0 | H44: 0 | I44: 0 | J44: 15 | K44: 84 | L44: 0 | M44: 0
D45: CMV 8 - 12 | F45: 0 | G45: 0 | H45: 0 | I45: 0 | J45: 52 | K45: 48 | L45: 0 | M45: 0 | Q45: Féverole
D46: CMV 8 - 16 | F46: 0 | G46: 0 | H46: 0 | I46: 0 | J46: 52 | K46: 64 | L46: 0 | M46: 0 | Q46: Graines de colza
D47: CMV 8 - 24 | F47: 0 | G47: 0 | H47: 0 | I47: 0 | J47: 52 | K47: 96 | L47: 0 | M47: 0 | Q47: Graines de coton
D48: CMV 9 - 14 | F48: 0 | G48: 0 | H48: 0 | I48: 0 | J48: 58 | K48: 56 | L48: 0 | M48: 0 | Q48: Graines de lin
D49: Drêches de blé | F49: 0.76 | G49: 0.68 | H49: 178 | I49: 157 | J49: 4.9 | K49: 1.3 | L49: 31 | M49: 6 | Q49: Graines de soja
D50: Drêches de brasserie | F50: 0.75 | G50: 0.67 | H50: 180 | I50: 160 | J50: 5 | K50: 1 | L50: 31.6 | M50: 6.1 | Q50: Graines de tournesol
D51: Féverole | F51: 1.03 | G51: 1.03 | H51: 170 | I51: 97 | J51: 4.1 | K51: 0.9 | L51: 31.1 | M51: 9.6 | Q51: Lupin
D52: Foin (prairies) | F52: 0.6 | G52: 0.5 | H52: 55 | I52: 65 | J52: 2 | K52: 1.5 | L52: 10 | M52: 33 | Q52: Pois
D53: Graines de colza | F53: 1.68 | G53: 1.68 | H53: 12 | I53: 61 | J53: 5.3 | K53: 2.8 | L53: 20.7 | M53: 8.9 | Q53: Vesce
D54: Graines de coton | F54: 0.94 | G54: 0.85 | H54: 131 | I54: 77 | J54: 5.1 | K54: 1 | L54: 23.4 | M54: 25.9
D55: Huile de colza | F55: 2.73 | G55: 2.78 | H55: 0 | I55: 0 | J55: 0 | K55: 0 | L55: 0 | M55: 0 | Q55: Bicarbonate de Na
D56: Lupin | F56: 1.18 | G56: 1.18 | H56: 213 | I56: 106 | J56: 3.2 | K56: 2.1 | L56: 38.5 | M56: 12.8 | Q56: Drêches de blé
D57: Luzerne (foin) | F57: 0.6 | G57: 0.5 | H57: 100 | I57: 80 | J57: 1.3 | K57: 3.8 | L57: 17 | M57: 36 | Q57: Drêches de brasserie
D58: Luzerne déshydratée | F58: 0.62 | G58: 0.54 | H58: 103 | I58: 91 | J58: 1.9 | K58: 6.5 | L58: 17.5 | M58: 29.5 | Q58: Huile de colza
D59: Maïs grain | F59: 1.06 | G59: 1.06 | H59: 64 | I59: 84 | J59: 2.2 | K59: 0.3 | L59: 9.4 | M59: 2.5 | Q59: Lactosérum
D60: Mélasse | F60: 0.75 | G60: 0.75 | H60: 63 | I60: 54 | J60: 0.2 | K60: 0.5 | L60: 14.5 | M60: 0 | Q60: Luzerne deshydratée
D61: Orge | F61: 0.95 | G61: 0.93 | H61: 69 | I61: 87 | J61: 3 | K61: 0.5 | L61: 11.6 | M61: 5.2 | Q61: Mélasse
D62: Paille de céréales | F62: 0.4 | G62: 0.35 | H62: 25 | I62: 45 | J62: 0.5 | K62: 1 | L62: 3.5 | M62: 42 | Q62: Poudre de lait écrémé
D63: Pois | F63: 1.04 | G63: 1.05 | H63: 130 | I63: 83 | J63: 3.4 | K63: 0.7 | L63: 23.9 | M63: 6 | Q63: Pulpe de betterave
D64: Poudre de lait écrémé | F64: 1.15 | G64: 1.17 | H64: 196 | I64: 75 | J64: 9.7 | K64: 11.7 | L64: 36 | M64: 0 | N64: 0
D65: Pulpe de betterave | F65: 0.89 | G65: 0.87 | H65: 59 | I65: 97 | J65: 0.9 | K65: 3 | L65: 9.1 | M65: 19.4 | N65: 100 | Q65: Carbonate de Ca
D66: Sarrazin | F66: 0.81 | G66: 0.76 | H66: 77 | I66: 82 | J66: 2.6 | K66: 0.5 | L66: 13.1 | M66: 11.6 | N66: 100 | Q66: CMV 0 - 27
D67: Seigle | F67: 1.03 | G67: 1.03 | H67: 59 | I67: 85 | J67: 2.6 | K67: 0.7 | L67: 10.3 | M67: 2.2 | N67: 120 | Q67: CMV 10 - 20
D68: Sorgho | F68: 1.05 | G68: 1.06 | H68: 67 | I68: 87 | J68: 2.4 | K68: 0.2 | L68: 109 | M68: 2.7 | N68: 120 | Q68: CMV 10 - 6
D69: Tourteau d'arachide | F69: 1 | G69: 0.97 | H69: 347 | I69: 215 | J69: 4.1 | K69: 1.2 | L69: 54.6 | M69: 7.6 | N69: 40 | Q69: CMV 12 - 12
D70: Tourteau de colza | F70: 0.85 | G70: 0.8 | H70: 219 | I70: 138 | J70: 9.2 | K70: 5.2 | L70: 35 | M70: 13.9 | N70: 50 | Q70: CMV 2 - 28
D71: Tourteau de lin | F71: 0.88 | G71: 0.84 | H71: 227 | I71: 179 | J71: 6 | K71: 2.8 | L71: 35.9 | M71: 11 | N71: 50 | Q71: CMV 3 - 27
D72: Tourteau de soja | F72: 1.06 | G72: 1.05 | H72: 331 | I72: 229 | J72: 5 | K72: 2.1 | L72: 51.6 | M72: 6.8 | N72: 60 | Q72: CMV 4 - 21
D73: Tourteau de tournesol | F73: 0.56 | G73: 0.46 | H73: 178 | I73: 93 | J73: 7.4 | K73: 2.4 | L73: 37.3 | M73: 23.6 | N73: 70 | Q73: CMV 5 - 20
D74: Triticale | F74: 1.01 | G74: 1.02 | H74: 63 | I74: 84 | J74: 3 | K74: 0.5 | L74: 11 | M74: 2.7 | N74: 80 | Q74: CMV 5 - 25
D75: Urée | F75: 0 | G75: 0 | H75: 1443 | I75: 0 | J75: 0 | K75: 0 | L75: 0 | M75: 0 | N75: 80 | Q75: CMV 6 - 6
D76: Vesce | F76: 1.02 | G76: 1.01 | H76: 161 | I76: 90 | J76: 3.8 | K76: 1 | L76: 29.6 | M76: 7.4 | N76: 80 | Q76: CMV 7 - 21
N77: 90 | Q77: CMV 8 - 12
N78: 0 | Q78: CMV 8 - 16
Q79: CMV 8 - 24
Q80: CMV 9 - 14
Q82: Paille de céréales
Q83: Luzerne (foin)
Q84: Foin (prairies)

Sheet IMPRIMER
B2: ALIM'ovins (v. 5.1) | F2: Nom:
B3: Rationnement des ovins allaitants
B7: Catégorie | E7: Apports Alimentaires Recommandés
E8: UEM | F8: UFL | G8: PDIN | H8: PDIE | I8: Pabs | J8: Caabs
B9: =IF(ANIMAL!E11="","",ANIMAL!E11) -> Brebis 70 kg Gestante Double Semaines - 3 à - 4 | E9: =IF($B$9="","",ANIMAL!E16) -> 1.71 | F9: =IF($B$9="","",ANIMAL!F16) -> 1.14 | G9: =IF($B$9="","",ANIMAL!G16) -> 146 | H9: =IF($B$9="","",ANIMAL!G16) -> 146 | I9: =IF($B$9="","",ANIMAL!H16) -> 3.2 | J9: =IF($B$9="","",ANIMAL!I16) -> 3.5
B11: Quantité kg | C11: Aliments (valeurs / kg MS) | D11: Valeurs alimentaires
D12: MS | E12: UEM | F12: UFL | G12: PDIN | H12: PDIE | I12: Pabs | J12: Caabs
B13: =IF(FOURRAGE!L10="","",FOURRAGE!L10) | C13: =FOURRAGE!E9 | D13: =FOURRAGE!E15 | E13: =FOURRAGE!F15 | F13: =FOURRAGE!G15 | G13: =FOURRAGE!H15 | H13: =FOURRAGE!I15 | I13: =FOURRAGE!J15 | J13: =FOURRAGE!L15
D14: =IF(B13="","",B13*(D13/100)) | E14: =IF($D$14="","",$D$14*E13) | F14: =IF($D$14="","",$D$14*F13) | G14: =IF($D$14="","",$D$14*G13) | H14: =IF($D$14="","",$D$14*H13) | I14: =IF($D$14="","",$D$14*I13) | J14: =IF($D$14="","",$D$14*J13)
B15: =IF(FOURRAGE!L24="","",FOURRAGE!L24) | C15: =FOURRAGE!E23 | D15: =IF(C15="","",FOURRAGE!E29) | E15: =IF(C15="","",FOURRAGE!F29) | F15: =IF(C15="","",FOURRAGE!G29) | G15: =IF(C15="","",FOURRAGE!H29) | H15: =IF(C15="","",FOURRAGE!I29) | I15: =IF(C15="","",FOURRAGE!J29) | J15: =IF(C15="","",FOURRAGE!L29)
D16: =IF(B15="","",B15*(D15/100)) | E16: =IF($D$16="","",$D$16*E15) | F16: =IF($D$16="","",$D$16*F15) | G16: =IF($D$16="","",$D$16*G15) | H16: =IF($D$16="","",$D$16*H15) | I16: =IF($D$16="","",$D$16*I15) | J16: =IF($D$16="","",$D$16*J15)
B17: =IF(SUM(B13,B15)=0,"",SUM(B13,B15)) | C17: Ration de base | D17: =IF(B17="","",SUM(D14,D16)) | E17: =IF(B17="","",SUM(E14,E16)) | F17: =IF(B17="","",SUM(F14,F16)) | G17: =IF(B17="","",SUM(G14,G16)) | H17: =IF(B17="","",SUM(H14,H16)) | I17: =IF(B17="","",SUM(I14,I16)) | J17: =IF(B17="","",SUM(J14,J16))
B19: Différence | E19: =IF(E9="","",E17-E9) -> #VALUE! | F19: =IF(F9="","",F17-F9) -> #VALUE! | G19: =IF(G9="","",G17-G9) -> #VALUE! | H19: =IF(H9="","",H17-H9) -> #VALUE! | I19: =IF(I9="","",I17-I9) -> #VALUE! | J19: =IF(J9="","",J17-J9) -> #VALUE!
B21: =IF(CONCENTRE!K9="","",CONCENTRE!K9) | C21: =IF(B21="","",CONCENTRE!C10) | F21: =IF(C21="","",CONCENTRE!E10) | G21: =IF(C21="","",CONCENTRE!F10) | H21: =IF(C21="","",CONCENTRE!G10) | I21: =IF(C21="","",CONCENTRE!H10) | J21: =IF(C21="","",CONCENTRE!I10)
F22: =IF(B21="","",$B$21*F21) | G22: =IF(B21="","",$B$21*G21) | H22: =IF(B21="","",$B$21*H21) | I22: =IF(B21="","",$B$21*I21) | J22: =IF(B21="","",$B$21*J21)
B23: =IF(CONCENTRE!K16="","",CONCENTRE!K16) | C23: =IF(B23="","",CONCENTRE!C17) | F23: =IF(C23="","",CONCENTRE!E17) | G23: =IF(C23="","",CONCENTRE!F17) | H23: =IF(C23="","",CONCENTRE!G17) | I23: =IF(C23="","",CONCENTRE!H17) | J23: =IF(C23="","",CONCENTRE!I17)
F24: =IF(B23="","",$B$23*F23) | G24: =IF(B23="","",$B$23*G23) | H24: =IF(B23="","",$B$23*H23) | I24: =IF(B23="","",$B$23*I23) | J24: =IF(B23="","",$B$23*J23)
B25: =IF(SUM(B21,B23)=0,"",SUM(B21,B23)) | C25: Concentrés | F25: =IF(B25="","",SUM(F22,F24)) | G25: =IF(B25="","",SUM(G22,G24)) | H25: =IF(B25="","",SUM(H22,H24)) | I25: =IF(B25="","",SUM(I22,I24)) | J25: =IF(B25="","",SUM(J22,J24))
B27: RMIC = | C27: PDIN - PDIE | D27: =IF(D30="","",(G30-H30)/F30) | E27: * | F27: =IF(CMV!C8="","",(CMV!C12)/1000) | G27: =IF(F27="","",CMV!L8) | I27: =CMV!G14 | J27: =CMV!I14
C28: UFL | I28: =IF(F27="","",I27*F27) | J28: =IF(F27="","",J27*F27)
B30: =IF(B17="","",SUM(B17,B25,F27)) | C30: TOTAL RATION | D30: =D17 | E30: =E17 | F30: =IF(F19="","",SUM(F25,F17)) -> #VALUE! | G30: =IF(G19="","",SUM(G25,G17)) -> #VALUE! | H30: =IF(H19="","",SUM(H25,H17)) -> #VALUE! | I30: =IF(I19="","",SUM(I25,I17,I28)) -> #VALUE! | J30: =IF(J19="","",SUM(J25,J17,J28)) -> #VALUE!
C32: Différence | E32: =IF(B17="","",E30-E9) | F32: =IF($B$17="","",F30-F9) | G32: =IF($B$17="","",G30-G9) | H32: =IF($B$17="","",H30-H9) | I32: =IF($B$17="","",I30-I9) | J32: =IF($B$17="","",J30-J9)
A33: * RMIC < - 12 (Brebis allaitantes - agneaux simples) RMIC < - 6 (Brebis allaitantes - agneaux doubles) | E33: =IF(E32="","",IF(E32>0,"ATTENTION ! La capacité d'ingestion est dépassée: REDUISEZ LES QUANTITES DE FOURRAGE",""))
A36: Commentaires: . . . . . . . . . . . . . . . . . . . . . . . . . . . . . . . . . . . . . . . . . . . . . . . . . . . . . . . . . . . . . . . . . . . . . . . . . . . .
A38: . . . . . . . . . . . . . . . . . . . . . . . . . . . . . . . . . . . . . . . . . . . . . . . . . . . . . . . . . . . . . . . . . . . . . . . . . . . . . . . . . . . . . . . . . . . . . .
A40: . . . . . . . . . . . . . . . . . . . . . . . . . . . . . . . . . . . . . . . . . . . . . . . . . . . . . . . . . . . . . . . . . . . . . . . . . . . . . . . . . . . . . . . . . . . . . .

Sheet IMPRIMCOUT
B2: ALIM'ovins(v. 5.1)
F3: Nom: | G3: OVIMASH Bélier
B4: FORMULATION ET CALCUL DU COUT D'UN CONCENTRE FERMIER
L5: =COUT!N6 -> 0 | M5: =COUT!O6 -> Coût des matières premières (€ /tonne)
B6: =COUT!B7 -> Quantités kg | C6: =COUT!C7 -> Matières premières | D6: =COUT!E7 -> Valeurs alimentaires
D7: =COUT!E8 -> % | E7: =COUT!F8 -> UFL | F7: =COUT!H8 -> PDIN | G7: =COUT!I8 -> PDIE | H7: =COUT!J8 -> Pabs | I7: =COUT!K8 -> Caabs | J7: MAT | K7: CB
B8: =IF(COUT!B9="","",COUT!B9) | C8: =IF(COUT!D9="","",COUT!D9) | D8: =COUT!E9 | E8: =COUT!F9 | F8: =COUT!H9 | G8: =COUT!I9 | H8: =COUT!J9 | I8: =COUT!K9 | J8: =COUT!L9 | K8: =COUT!M9
E9: =COUT!F10 | F9: =COUT!H10 | G9: =COUT!I10 | H9: =COUT!J10 | I9: =COUT!K10 | J9: =COUT!L10 | K9: =COUT!M10 | M9: =COUT!O10 -> 0
B10: =IF(COUT!B11="","",COUT!B11) | C10: =IF(COUT!D11="","",COUT!D11) | D10: =COUT!E11 | E10: =COUT!F11 | F10: =COUT!H11 | G10: =COUT!I11 | H10: =COUT!J11 | I10: =COUT!K11 | J10: =COUT!L11 | K10: =COUT!M11
E11: =COUT!F12 | F11: =COUT!H12 | G11: =COUT!I12 | H11: =COUT!J12 | I11: =COUT!K12 | J11: =COUT!L12 | K11: =COUT!M12 | M11: =COUT!O12 -> 0
B12: =IF(COUT!B13="","",COUT!B13) | C12: =IF(COUT!D13="","",COUT!D13) | D12: =COUT!E13 | E12: =COUT!F13 | F12: =COUT!H13 | G12: =COUT!I13 | H12: =COUT!J13 | I12: =COUT!K13 | J12: =COUT!L13 | K12: =COUT!M13
E13: =COUT!F14 | F13: =COUT!H14 | G13: =COUT!I14 | H13: =COUT!J14 | I13: =COUT!K14 | J13: =COUT!L14 | K13: =COUT!M14 | M13: =COUT!O14 -> 0
B14: =IF(COUT!B15="","",COUT!B15) | C14: =IF(COUT!D15="","",COUT!D15) | D14: =COUT!E15 | E14: =COUT!F15 | F14: =COUT!H15 | G14: =COUT!I15 | H14: =COUT!J15 | I14: =COUT!K15 | J14: =COUT!L15 | K14: =COUT!M15
E15: =COUT!F16 | F15: =COUT!H16 | G15: =COUT!I16 | H15: =COUT!J16 | I15: =COUT!K16 | J15: =COUT!L16 | K15: =COUT!M16 | M15: =COUT!O16 -> 0
B16: =IF(COUT!B17="","",COUT!B17) | C16: =IF(COUT!D17="","",COUT!D17) | D16: =COUT!E17 | E16: =COUT!F17 | F16: =COUT!H17 | G16: =COUT!I17 | H16: =COUT!J17 | I16: =COUT!K17 | J16: =COUT!L17 | K16: =COUT!M17
E17: =COUT!F18 | F17: =COUT!H18 | G17: =COUT!I18 | H17: =COUT!J18 | I17: =COUT!K18 | J17: =COUT!L18 | K17: =COUT!M18 | M17: =COUT!O18 -> 0
B18: =IF(COUT!B19="","",COUT!B19) | C18: =IF(COUT!D19="","",COUT!D19) | D18: =COUT!E19 | E18: =COUT!F19 | F18: =COUT!H19 | G18: =COUT!I19 | H18: =COUT!J19 | I18: =COUT!K19 | J18: =COUT!L19 | K18: =COUT!M19
E19: =COUT!F20 | F19: =COUT!H20 | G19: =COUT!I20 | H19: =COUT!J20 | I19: =COUT!K20 | J19: =COUT!L20 | K19: =COUT!M20 | M19: =COUT!O20 -> 0
M21: =COUT!O22 -> COUT € / kg
B22: =COUT!B23 -> 0 | C22: =COUT!D23 -> Mon aliment | D22: =COUT!E23 | E22: =COUT!F23 | F22: =COUT!H23 | G22: =COUT!I23 | H22: =COUT!J23 | I22: =COUT!K23 | J22: =COUT!L23 | K22: =COUT!M23 | L22: =COUT!N23 -> 0 | M22: =COUT!O23
C27: Catégorie | D27: C | E27: U.F.L. | F27: P.D.I.N. | G27: P.D.I.E. | H27: Pabs | I27: Caabs
C28: Aliment complet | E28: =#REF! -> #REF! | F28: =#REF! -> #REF! | G28: =#REF! -> #REF! | H28: =#REF! -> #REF! | I28: =#REF! -> #REF!
C29: Aliment divers | E29: =#REF! -> #REF! | F29: =#REF! -> #REF! | G29: =#REF! -> #REF! | H29: =#REF! -> #REF! | I29: =#REF! -> #REF!
C30: Avoine | E30: 0.77 | F30: 61 | G30: 61 | H30: 2.7 | I30: 0.7
C31: Bicarbonate de Na | E31: 0 | F31: 0 | G31: 0 | H31: 0 | I31: 0
C32: Blé | E32: 1.02 | F32: 70 | G32: 89 | H32: 2.6 | I32: 0.4
C33: Carbonate de Ca | E33: 0 | F33: 0 | G33: 0 | H33: 0 | I33: 150
C34: CMV 0 - 27 (Gravelle) | E34: 0 | F34: 0 | G34: 0 | H34: 0 | I34: 108
C35: CMV 10 - 20 | E35: 0 | F35: 0 | G35: 0 | H35: 65 | I35: 80
C36: CMV 10 - 6 | E36: 0 | F36: 0 | G36: 0 | H36: 65 | I36: 24
C37: CMV 12 - 12 | E37: 0 | F37: 0 | G37: 0 | H37: 78 | I37: 48
C38: CMV 12 - 12 | E38: 0 | F38: 0 | G38: 0 | H38: 78 | I38: 48
C39: CMV 4 - 21 | E39: 0 | F39: 0 | G39: 0 | H39: 26 | I39: 84
C40: CMV 5 - 20 | E40: 0 | F40: 0 | G40: 0 | H40: 32 | I40: 80
C41: CMV 5 - 25 | E41: 0 | F41: 0 | G41: 0 | H41: 32 | I41: 100
... C47: CMV 9 - 14 | E47: 0 | F47: 0 | G47: 0 | H47: 58 | I47: 56
C48: Complémentaire azoté | E48: =#REF! -> #REF! | F48: =#REF! -> #REF! | G48: =#REF! -> #REF! | H48: =#REF! -> #REF! | I48: =#REF! -> #REF!
C49: Drêches | E49: 0.76 | F49: 178 | G49: 157 | H49: 4.9 | I49: 1.3
C50: Féverole | E50: 1.03 | F50: 170 | G50: 97 | H50: 4.1 | I50: 0.9
C51: Graines Colza | E51: 1.68 | F51: 12 | G51: 61 | H51: 5.3 | I51: 2.8
C52: Graines Coton | E52: 0.94 | F52: 131 | G52: 77 | H52: 5.1 | I52: 1
C53: Huile de colza | E53: 2.73 | F53: 0 | G53: 0 | H53: 0 | I53: 0
C54: Lupin Blanc | E54: 1.18 | F54: 213 | G54: 106 | H54: 3.2 | I54: 2.1
C55: Luzerne déhydratée | E55: 0.62 | F55: 103 | G55: 91 | H55: 1.9 | I55: 6.5
C56: Maïs grain | E56: 1.06 | F56: 64 | G56: 84 | H56: 2.2 | I56: 0.3
C57: Mélange 2/3 O - 1/3 S | E57: 0.98666667 | F57: 156.33333 | G57: 134.33333 | H57: 3.6666667 | I57: 1.0333333
C58: Mélange 2/3 T - 1/3 C | E58: 0.95666667 | F58: 115 | G58: 102 | H58: 5.0666667 | I58: 2.0666667
C59: Mélange 3/4 O - 1/4 S | E59: 0.9775 | F59: 134.5 | G59: 122.5 | H59: 3.5 | I59: 0.9
C60: Mélange 80 % O - 20 % S | E60: 0.972 | F60: 121.4 | G60: 115.4 | H60: 3.4 | I60: 0.82
C61: Mélasse | E61: 0.75 | F61: 63 | G61: 54 | H61: 0.2 | I61: 0.5
C62: Mon concentré | E62: =COUT!F7 -> 0 | F62: =COUT!H7 -> 0 | G62: =COUT!I7 -> 0 | H62: =COUT!J7 -> 0 | I62: =COUT!K7 -> 0
C63: Orge | E63: 0.95 | F63: 69 | G63: 87 | H63: 3 | I63: 0.5 | L63: 0
C64: Pois | E64: 1.04 | F64: 130 | G64: 83 | H64: 3.4 | I64: 0.7 | L64: 100
C65: Poudre de lait écrémé | E65: 1.15 | F65: 196 | G65: 75 | H65: 9.7 | I65: 11.7 | L65: 100
C66: Pulpe de betterave | E66: 0.89 | F66: 59 | G66: 97 | H66: 0.9 | I66: 3 | L66: 120
C67: Sarrazin | E67: 0.81 | F67: 77 | G67: 82 | H67: 2.6 | I67: 0.5 | L67: 120
C68: Seigle | E68: 1.03 | F68: 59 | G68: 85 | H68: 2.6 | I68: 0.7 | L68: 40
C69: Sorgho | E69: 1.05 | F69: 67 | G69: 87 | H69: 2.4 | I69: 0.2 | L69: 50
C70: Tourteau Arachide | E70: 1 | F70: 347 | G70: 215 | H70: 4.1 | I70: 1.2 | L70: 50
C71: Tourteau Colza 35 | E71: 0.85 | F71: 219 | G71: 138 | H71: 9.2 | I71: 5.2 | L71: 60
C72: Tourteau Lin | E72: 0.88 | F72: 227 | G72: 179 | H72: 6 | I72: 2.8 | L72: 70
C73: Tourteau Soja 48 | E73: 1.06 | F73: 331 | G73: 229 | H73: 5 | I73: 2.1 | L73: 80
C74: Tourteau Tournesol | E74: 0.56 | F74: 178 | G74: 93 | H74: 7.4 | I74: 2.4 | L74: 80
... C77: Vesce | E77: 1.02 | F77: 161 | G77: 90 | H77: 3.8 | I77: 1 | L77: 0

Sheet AGNEAU
B1: ALIM'ovins(v. 5.1)
B2: Rationnement des ovins
B4: Agneau
U5: 3 Composez votre concentré "agneau"
B6: 1 Cliquez sur les flèches ou cochez les cases | F6: CATEGORIE | L6: CHOIX DU CONCENTRE
U7: % | V7: Matières premières | X7: Valeurs alimentaires
E8: =IF(C12="","",CONCATENATE(IF(I33=1,"mâle","femelle")," de race ",IF(I36=TRUE,"à viande","rustique ou croisée")," poids ",C12," - GMQ ",C14)) | X8: UFV | Y8: PDIN | Z8: PDIE | AA8: Pabs | AB8: Caabs
L9: Valeur U.F.V. de l'aliment | P9: =IF(E8="","",M38) | Q9: =IF(P9="","","UFV / kg") | X9: =IF(U9="","",IF(V9="Mes_concentrés",VLOOKUP(W9,NOUVEAU!$R$22:$AA$38,4),VLOOKUP($W9,$W44:$AC93,3))) | Y9: =IF(U9="","",IF(V9="Mes_concentrés",VLOOKUP(W9,NOUVEAU!$R$22:$AA$38,5),VLOOKUP($W9,$W44:$AC93,4))) | Z9: =IF(U9="","",IF(V9="Mes_concentrés",VLOOKUP(W9,NOUVEAU!$R$22:$AA$38,6),VLOOKUP($W9,$W44:$AC93,5))) | AA9: =IF(U9="","",IF(V9="Mes_concentrés",VLOOKUP(W9,NOUVEAU!$R$22:$AA$38,7),VLOOKUP($W9,$W44:$AC93,6))) | AB9: =IF(U9="","",IF(V9="Mes_concentrés",VLOOKUP(W9,NOUVEAU!$R$22:$AA$38,8),VLOOKUP($W9,$W44:$AC93,7)))
X10: =IF(U9="","",($U$9/100)*X9) | Y10: =IF(U9="","",($U$9/100)*Y9) | Z10: =IF(U9="","",($U$9/100)*Z9) | AA10: =IF(U9="","",($U$9/100)*AA9) | AB10: =IF(U9="","",($U$9/100)*AB9)
M11: 2 | N11: faites varier la teneur avec les flèches | X11: =IF(U11="","",IF(V11="Mes_concentrés",VLOOKUP(W11,NOUVEAU!$R$22:$AA$38,4),VLOOKUP($W11,$W44:$AC93,3))) | Y11: =IF(U11="","",IF(V11="Mes_concentrés",VLOOKUP(W11,NOUVEAU!$R$22:$AA$38,5),VLOOKUP($W11,$W44:$AC93,4))) | Z11: =IF(U11="","",IF(V11="Mes_concentrés",VLOOKUP(W11,NOUVEAU!$R$22:$AA$38,6),VLOOKUP($W11,$W44:$AC93,5))) | AA11: =IF(U11="","",IF(V11="Mes_concentrés",VLOOKUP(W11,NOUVEAU!$R$22:$AA$38,7),VLOOKUP($W11,$W44:$AC93,6))) | AB11: =IF(U11="","",IF(V11="Mes_concentrés",VLOOKUP(W11,NOUVEAU!$R$22:$AA$38,8),VLOOKUP($W11,$W44:$AC93,7)))
B12: Poids | E12: BESIONS ALIMENTAIRES | X12: =IF(U11="","",($U$11/100)*X11) | Y12: =IF(U11="","",($U$11/100)*Y11) | Z12: =IF(U11="","",($U$11/100)*Z11) | AA12: =IF(U11="","",($U$11/100)*AA11) | AB12: =IF(U11="","",($U$11/100)*AB11)
E13: U.F.V. | F13: P.D.I. | G13: Pabs | H13: Caabs | M13: Quantités nécessaires | P13: =IF(E8="","",IF(E14="ND","",E14/P9)) | Q13: =IF(E8="","","kg /jour") | X13: =IF(U13="","",IF(V13="Mes_concentrés",VLOOKUP(W13,NOUVEAU!$R$22:$AA$38,4),VLOOKUP($W13,$W44:$AC93,3))) | Y13: =IF(U13="","",IF(V13="Mes_concentrés",VLOOKUP(W13,NOUVEAU!$R$22:$AA$38,5),VLOOKUP($W13,$W44:$AC93,4))) | Z13: =IF(U13="","",IF(V13="Mes_concentrés",VLOOKUP(W13,NOUVEAU!$R$22:$AA$38,6),VLOOKUP($W13,$W44:$AC93,5))) | AA13: =IF(U13="","",IF(V13="Mes_concentrés",VLOOKUP(W13,NOUVEAU!$R$22:$AA$38,7),VLOOKUP($W13,$W44:$AC93,6))) | AB13: =IF(U13="","",IF(V13="Mes_concentrés",VLOOKUP(W13,NOUVEAU!$R$22:$AA$38,8),VLOOKUP($W13,$W44:$AC93,7)))
B14: GMQ | E14: =IF(E8="","",VLOOKUP(E8,G43:K211,2)) | F14: =IF(E8="","",VLOOKUP(E8,G43:K211,3)) | G14: =IF(E8="","",VLOOKUP(E8,G43:K211,4)) | H14: =IF(E8="","",VLOOKUP(E8,G43:K211,5)) | X14: =IF(U13="","",($U$13/100)*X13) | Y14: =IF(U13="","",($U$13/100)*Y13) | Z14: =IF(U13="","",($U$13/100)*Z13) | AA14: =IF(U13="","",($U$13/100)*AA13) | AB14: =IF(Z13="","",($U$13/100)*AB13)
X15: =IF(U15="","",IF(V15="Mes_concentrés",VLOOKUP(W15,NOUVEAU!$R$22:$AA$38,4),VLOOKUP($W15,$W44:$AC93,3))) | Y15: =IF(U15="","",IF(V15="Mes_concentrés",VLOOKUP(W15,NOUVEAU!$R$22:$AA$38,5),VLOOKUP($W15,$W44:$AC93,4))) | Z15: =IF(U15="","",IF(V15="Mes_concentrés",VLOOKUP(W15,NOUVEAU!$R$22:$AA$38,6),VLOOKUP($W15,$W44:$AC93,5))) | AA15: =IF(U15="","",IF(V15="Mes_concentrés",VLOOKUP(W15,NOUVEAU!$R$22:$AA$38,7),VLOOKUP($W15,$W44:$AC93,6))) | AB15: =IF(U15="","",IF(V15="Mes_concentrés",VLOOKUP(W15,NOUVEAU!$R$22:$AA$38,8),VLOOKUP($W15,$W44:$AC93,7)))
X16: =IF(U15="","",($U$15/100)*X15) | Y16: =IF(U15="","",($U$15/100)*Y15) | Z16: =IF(U15="","",($U$15/100)*Z15) | AA16: =IF(U15="","",($U$15/100)*AA15) | AB16: =IF(U15="","",($U$15/100)*AB15)
C17: COMPOSITION DE L'ALIMENT | K17: DUREE D'ENGRAISSEMENT (jours restants jusqu'à 40 kg) | X17: =IF(U17="","",IF(V17="Mes_concentrés",VLOOKUP(W17,NOUVEAU!$R$22:$AA$38,4),VLOOKUP($W17,$W44:$AC93,3))) | Y17: =IF(U17="","",IF(V17="Mes_concentrés",VLOOKUP(W17,NOUVEAU!$R$22:$AA$38,5),VLOOKUP($W17,$W44:$AC93,4))) | Z17: =IF(U17="","",IF(V17="Mes_concentrés",VLOOKUP(W17,NOUVEAU!$R$22:$AA$38,6),VLOOKUP($W17,$W44:$AC93,5))) | AA17: =IF(U17="","",IF(V17="Mes_concentrés",VLOOKUP(W17,NOUVEAU!$R$22:$AA$38,7),VLOOKUP($W17,$W44:$AC93,6))) | AB17: =IF(U17="","",IF(V17="Mes_concentrés",VLOOKUP(W17,NOUVEAU!$R$22:$AA$38,8),VLOOKUP($W17,$W44:$AC93,7)))
C18: U.F.V. | D18: P.D.I. | F18: Pabs | G18: Caabs | H18: Ca / P | X18: =IF(U17="","",($U$17/100)*X17) | Y18: =IF(U17="","",($U$17/100)*Y17) | Z18: =IF(U17="","",($U$17/100)*Z17) | AA18: =IF(U17="","",($U$17/100)*AA17) | AB18: =IF(U17="","",($U$17/100)*AB17)
B19: / kg brut | C19: =P9 | D19: =IF(E8="","",F14/P13) | F19: =IF(E8="","",G14/P13) | G19: =IF(E8="","",H14/P13) | H19: =IF(E8="","",G19/F19) | X19: =IF(U19="","",IF(V19="Mes_concentrés",VLOOKUP(W19,NOUVEAU!$R$22:$AA$38,4),VLOOKUP($W19,$W44:$AC93,3))) | Y19: =IF(U19="","",IF(V19="Mes_concentrés",VLOOKUP(W19,NOUVEAU!$R$22:$AA$38,5),VLOOKUP($W19,$W44:$AC93,4))) | Z19: =IF(U19="","",IF(V19="Mes_concentrés",VLOOKUP(W19,NOUVEAU!$R$22:$AA$38,6),VLOOKUP($W19,$W44:$AC93,5))) | AA19: =IF(U19="","",IF(V19="Mes_concentrés",VLOOKUP(W19,NOUVEAU!$R$22:$AA$38,7),VLOOKUP($W19,$W44:$AC93,6))) | AB19: =IF(U19="","",IF(V19="Mes_concentrés",VLOOKUP(W19,NOUVEAU!$R$22:$AA$38,8),VLOOKUP($W19,$W44:$AC93,7)))
K20: =(40-Q34)/(Q35/1000) -> 0 | O20: jours | X20: =IF(U19="","",($U$19/100)*X19) | Y20: =IF(U19="","",($U$19/100)*Y19) | Z20: =IF(U19="","",($U$19/100)*Z19) | AA20: =IF(U19="","",($U$19/100)*AA19) | AB20: =IF(U19="","",($U$19/100)*AB19)
U21: =IF(SUM(U9,U11,U13,U15,U17,U19)=0,"",SUM(U9:U20)) | W21: Concentrés | X21: =IF(U9="","",SUM(X10,X12,X14,X16,X18,X20)) | Y21: =IF(U9="","",SUM(Y10,Y12,Y14,Y16,Y18,Y20)) | Z21: =IF(U9="","",SUM(Z10,Z12,Z14,Z16,Z18,Z20)) | AA21: =IF(U9="","",SUM(AA10,AA12,AA14,AA16,AA18,AA20)) | AB21: =IF(U9="","",SUM(AB10,AB12,AB14,AB16,AB18,AB20))
C23: Saisissez le prix de l'aliment et le nombre d'agneaux | H23: QUANTITES D'ALIMENTS ET COUTS | U23: =CONCATENATE(" Votre aliment contient ",ROUND(Q62,1)," % de MAT et ",ROUND(Q74,1)," % de Cellulose") -> Votre aliment contient 0 % de MAT et 0 % de Cellulose
B24: Prix de l'aliment (€ / tonne) | F24: Aliment / jour | H24: =IF(D27="","",P13*D27) | J24: =IF(H24="","","kg") | L24: Quantité totale d'aliment à prévoir | P24: Cout total | U24: =IF(U21=100,"",IF(U21>100,">100%","<100%")) -> >100% | W24: Différence | X24: =IF(U9="","",X21-C19) | Y24: =IF(U9="","",Y21-D19) | Z24: =IF(U9="","",Z21-D19) | AA24: =IF(U9="","",AA21-F19) | AB24: =IF(U9="","",AB21-G19)
L26: =IF(D27="","",H24*K20) | N26: =IF(L26="","","kg") | P26: =IF(D27="","",(D24*L26)/1000)
B27: Nombre d'agneaux | F27: Cout /jour | H27: =IF(D27="","",(P13*D24*D27)/1000) | T27: =IF(U9="","",IF(Q74<6,"ATTENTION ! aliment acidogène: augmentez la cellulose","")) | W27: =IF(U9="","",IF(C19>X21+0.03,"Augmentez l'énergie (céréales...)",IF(C19<X21-0.03,"Diminuez l'énergie (Pulpe…)",""))) | Y27: =IF(U9="","",IF(Y24>5,"Diminez l'azote (Céréales, pulpe…)",IF(Y24<-5,"Augmentez l'azote (Tourteau, luzerne…)","")))
E32: 150 g | F32: Viande | H32: 15 kg | I32: Mâle/Femelle
E33: 200 g | F33: Rustique | H33: 20 kg | I33: 1
E34: 250 g | F34: Laitière | H34: 25 kg | N34: #REF! | Q34: =IF(C12="15 kg",15,IF(C12="20 kg",20,IF(C12="25 kg",25,IF(C12="30 kg",30,IF(C12="35 kg",35,40))))) -> 40
E35: 300 g | F35: Croisée | H35: 30 kg | I35: Viande/Rustique | Q35: =IF(C14="150 g",150,IF(C14="200 g",200,IF(C14="250 g",250,IF(C14="300 g",300,IF(C14="350 g",350,IF(C14="400 g",400,450)))))) -> 450
E36: 350 g | H36: 35 kg | I36: TRUE
E37: 400 g | H37: 40 kg
E38: 450 g | L38: 1 | M38: =IF(L38=1,0.8,IF(L38=2,0.85,IF(L38=3,0.9,IF(L38=4,0.95,1)))) -> 0.8
H40: 0 | J40: UFV / kg
C43: Poids vif | D43: GMQ | E43: Potentiel | F43: sexe | H43: UFV | I43: PDI | J43: P | K43: Ca | W43: Catégorie | X43: Cu | Y43: U.F.V. | Z43: P.D.I.N. | AA43: P.D.I.E. | AB43: Pabs | AC43: Caabs | AD43: MAT | AE43: CB
C44: 15 kg | D44: 150 g | E44: Elevé | F44: femelle | G44: femelle de race à viande poids 15 kg - GMQ 150 g | H44: ND | I44: ND | J44: ND | K44: ND | L44: 22 | Q44: Céréale | W44: Avoine | X44: 3 | Y44: 0.71 | Z44: 61 | AA44: 61 | AB44: 2.4 | AC44: 0.6 | AD44: 11.1 | AE44: 13.8
C45: 15 kg | D45: 200 g | E45: Elevé | F45: femelle | G45: femelle de race à viande poids 15 kg - GMQ 200 g | H45: ND | I45: ND | J45: ND | K45: ND | L45: 23 | Q45: Tourteau | W45: Bicarbonate de Na | X45: 0 | Y45: 0 | Z45: 0 | AA45: 0 | AB45: 0 | AC45: 0 | AD45: 0 | AE45: 0
C46: 15 kg | D46: 250 g | E46: Elevé | F46: femelle | G46: femelle de race à viande poids 15 kg - GMQ 250 g | H46: ND | I46: ND | J46: ND | K46: ND | L46: 24 | Q46: Graines | W46: Blé | X46: 5 | Y46: 1.02 | Z46: 70 | AA46: 89 | AB46: 2.3 | AC46: 0.3 | AD46: 12.1 | AE46: 2.6
C47: 15 kg | D47: 300 g | E47: Elevé | F47: femelle | G47: femelle de race à viande poids 15 kg - GMQ 300 g | H47: ND | I47: ND | J47: ND | K47: ND | L47: 25 | Q47: Divers | W47: Carbonate de Ca | X47: 0 | Y47: 0 | Z47: 0 | AA47: 0 | AB47: 0 | AC47: 150 | AD47: 0 | AE47: 0
C48: 15 kg | D48: 350 g | E48: Elevé | F48: femelle | G48: femelle de race à viande poids 15 kg - GMQ 350 g | H48: ND | I48: ND | J48: ND | K48: ND | L48: 26 | Q48: Minéraux | W48: CMV 0 - 27 | Y48: 0 | Z48: 0 | AA48: 0 | AB48: 0 | AC48: 108 | AD48: 0 | AE48: 0
C49: 15 kg | D49: 400 g | E49: Elevé | F49: femelle | G49: femelle de race à viande poids 15 kg - GMQ 400 g | H49: ND | I49: ND | J49: ND | K49: ND | L49: 27 | Q49: Mes_concentrés | W49: CMV 10 - 20 | Y49: 0 | Z49: 0 | AA49: 0 | AB49: 65 | AC49: 80 | AD49: 0 | AE49: 0
C50: 15 kg | D50: 450 g | E50: Elevé | F50: femelle | G50: femelle de race à viande poids 15 kg - GMQ 450 g | H50: ND | I50: ND | J50: ND | K50: ND | L50: 28 | W50: CMV 10 - 6 | Y50: 0 | Z50: 0 | AA50: 0 | AB50: 65 | AC50: 24 | AD50: 0 | AE50: 0
C51: 20 kg | D51: 150 g | E51: Elevé | F51: femelle | G51: femelle de race à viande poids 20 kg - GMQ 150 g | H51: 0.73 | I51: 67 | J51: 1.9 | K51: 4.6 | L51: 50 | W51: CMV 12 - 12 | Y51: 0 | Z51: 0 | AA51: 0 | AB51: 78 | AC51: 48 | AD51: 0 | AE51: 0
C52: 20 kg | D52: 200 g | E52: Elevé | F52: femelle | G52: femelle de race à viande poids 20 kg - GMQ 200 g | H52: 0.77 | I52: 80 | J52: 2.3 | K52: 5.7 | L52: 51 | W52: CMV 4 - 21 | Y52: 0 | Z52: 0 | AA52: 0 | AB52: 26 | AC52: 84 | AD52: 0 | AE52: 0
C53: 20 kg | D53: 250 g | E53: Elevé | F53: femelle | G53: femelle de race à viande poids 20 kg - GMQ 250 g | H53: 0.8 | I53: 93 | J53: 2.7 | K53: 6.8 | L53: 52 | W53: CMV 5 - 20 | Y53: 0 | Z53: 0 | AA53: 0 | AB53: 32 | AC53: 80 | AD53: 0 | AE53: 0
C54: 20 kg | D54: 300 g | E54: Elevé | F54: femelle | G54: femelle de race à viande poids 20 kg - GMQ 300 g | H54: 0.82 | I54: 106 | J54: 3 | K54: 8 | L54: 53 | P54: =U9 -> 0 | Q54: =VLOOKUP(W9,$W$44:$AD$93,8) -> #N/A | R54: =IF(P54=0,0,(Q54/100)*(P54/100)) -> 0 | W54: CMV 5 - 22 | Y54: 0 | Z54: 0 | AA54: 0 | AB54: 32 | AC54: 90 | AD54: 0 | AE54: 0
C55: 20 kg | D55: 350 g | E55: Elevé | F55: femelle | G55: femelle de race à viande poids 20 kg - GMQ 350 g | H55: ND | I55: ND | J55: ND | K55: ND | L55: 54 | P55: =U11 -> 0 | Q55: =VLOOKUP(W11,$W$44:$AD$93,8) -> #N/A | R55: =IF(P55=0,0,(Q55/100)*(P55/100)) -> 0 | W55: CMV 5 - 25 | Y55: 0 | Z55: 0 | AA55: 0 | AB55: 32 | AC55: 100 | AD55: 0 | AE55: 0
C56: 20 kg | D56: 400 g | E56: Elevé | F56: femelle | G56: femelle de race à viande poids 20 kg - GMQ 400 g | H56: ND | I56: ND | J56: ND | K56: ND | L56: 55 | P56: =U13 -> 0 | Q56: =VLOOKUP(W13,$W$44:$AD$93,8) -> #N/A | R56: =IF(P56=0,0,(Q56/100)*(P56/100)) -> 0 | W56: CMV 6 - 6 | Y56: 0 | Z56: 0 | AA56: 0 | AB56: 39 | AC56: 24 | AD56: 0 | AE56: 0
C57: 20 kg | D57: 450 g | E57: Elevé | F57: femelle | G57: femelle de race à viande poids 20 kg - GMQ 450 g | H57: ND | I57: ND | J57: ND | K57: ND | L57: 56 | P57: =U15 -> 0 | Q57: =VLOOKUP(W15,$W$44:$AD$93,8) -> #N/A | R57: =IF(P57=0,0,(Q57/100)*(P57/100)) -> 0 | W57: CMV 7 - 21 | Y57: 0 | Z57: 0 | AA57: 0 | AB57: 15 | AC57: 84 | AD57: 0 | AE57: 0
C58: 25 kg | D58: 150 g | E58: Elevé | F58: femelle | G58: femelle de race à viande poids 25 kg - GMQ 150 g | H58: 0.82 | I58: 69 | J58: 2.2 | K58: 5.2 | L58: 78 | P58: =U17 -> 0 | Q58: =VLOOKUP(W17,$W$44:$AD$93,8) -> #N/A | R58: =IF(P58=0,0,(Q58/100)*(P58/100)) -> 0 | W58: CMV 8 - 12 | Y58: 0 | Z58: 0 | AA58: 0 | AB58: 52 | AC58: 48 | AD58: 0 | AE58: 0
C59: 25 kg | D59: 200 g | E59: Elevé | F59: femelle | G59: femelle de race à viande poids 25 kg - GMQ 200 g | H59: 0.85 | I59: 82 | J59: 2.6 | K59: 6.4 | L59: 79 | P59: =U19 -> 0 | Q59: =VLOOKUP(W19,$W$44:$AD$93,8) -> #N/A | R59: =IF(P59=0,0,(Q59/100)*(P59/100)) -> 0 | W59: CMV 8 - 16 | Y59: 0 | Z59: 0 | AA59: 0 | AB59: 52 | AC59: 64 | AD59: 0 | AE59: 0
C60: 25 kg | D60: 250 g | E60: Elevé | F60: femelle | G60: femelle de race à viande poids 25 kg - GMQ 250 g | H60: 0.89 | I60: 94 | J60: 3 | K60: 7.6 | L60: 80 | W60: CMV 8 - 24 | Y60: 0 | Z60: 0 | AA60: 0 | AB60: 52 | AC60: 96 | AD60: 0 | AE60: 0
C61: 25 kg | D61: 300 g | E61: Elevé | F61: femelle | G61: femelle de race à viande poids 25 kg - GMQ 300 g | H61: 0.92 | I61: 107 | J61: 3.3 | K61: 8.9 | L61: 81 | W61: CMV 9 - 14 | Y61: 0 | Z61: 0 | AA61: 0 | AB61: 58 | AC61: 56 | AD61: 0 | AE61: 0
C62: 25 kg | D62: 350 g | E62: Elevé | F62: femelle | G62: femelle de race à viande poids 25 kg - GMQ 350 g | H62: 0.95 | I62: 119 | J62: 3.7 | K62: 10.3 | L62: 82 | Q62: =SUM(R54:R59)*100 -> 0 | R62: MAT | W62: Drêches de blé | X62: 18 | Y62: 0.67 | Z62: 178 | AA62: 157 | AB62: 4.5 | AC62: 1.2 | AD62: 31.6 | AE62: 6.1
C63: 25 kg | D63: 400 g | E63: Elevé | F63: femelle | G63: femelle de race à viande poids 25 kg - GMQ 400 g | H63: ND | I63: ND | J63: ND | K63: ND | L63: 83 | W63: Féverole | X63: 11 | Y63: 1.03 | Z63: 170 | AA63: 97 | AB63: 3.5 | AC63: 0.8 | AD63: 31.1 | AE63: 9.6
C64: 25 kg | D64: 450 g | E64: Elevé | F64: femelle | G64: femelle de race à viande poids 25 kg - GMQ 450 g | H64: ND | I64: ND | J64: ND | K64: ND | L64: 84 | W64: Graines de colza | X64: 3 | Y64: 1.68 | Z64: 12 | AA64: 61 | AB64: 4.9 | AC64: 2.6 | AD64: 20.7 | AE64: 8.9
C65: 30 kg | D65: 150 g | E65: Elevé | F65: femelle | G65: femelle de race à viande poids 30 kg - GMQ 150 g | H65: 0.91 | I65: 72 | J65: 2.4 | K65: 5.8 | L65: 106 | W65: Graines de coton | X65: 10 | Y65: 0.85 | Z65: 131 | AA65: 77 | AB65: 4.6 | AC65: 0.9 | AD65: 23.4 | AE65: 25.9
C66: 30 kg | D66: 200 g | E66: Elevé | F66: femelle | G66: femelle de race à viande poids 30 kg - GMQ 200 g | H66: 0.96 | I66: 84 | J66: 2.8 | K66: 7.1 | L66: 107 | P66: =U9 -> 0 | Q66: =VLOOKUP(W9,$W$44:$AE$93,9) -> #N/A | R66: =IF(P66=0,0,(Q66/100)*(P66/100)) -> 0 | W66: Huile de colza | X66: 0 | Y66: 2.78 | Z66: 0 | AA66: 0 | AB66: 0 | AC66: 0 | AD66: 0 | AE66: 0
C67: 30 kg | D67: 250 g | E67: Elevé | F67: femelle | G67: femelle de race à viande poids 30 kg - GMQ 250 g | H67: 1.01 | I67: 95 | J67: 3.2 | K67: 8.5 | L67: 108 | P67: =U11 -> 0 | Q67: =VLOOKUP(W11,$W$44:$AE$93,9) -> #N/A | R67: =IF(P67=0,0,(Q67/100)*(P67/100)) -> 0 | W67: Lupin | X67: 4 | Y67: 1.18 | Z67: 213 | AA67: 106 | AB67: 2.8 | AC67: 1.9 | AD67: 38.5 | AE67: 12.8
C68: 30 kg | D68: 300 g | E68: Elevé | F68: femelle | G68: femelle de race à viande poids 30 kg - GMQ 300 g | H68: 1.04 | I68: 107 | J68: 3.6 | K68: 9.7 | L68: 109 | P68: =U13 -> 0 | Q68: =VLOOKUP(W13,$W$44:$AE$93,9) -> #N/A | R68: =IF(P68=0,0,(Q68/100)*(P68/100)) -> 0 | W68: Luzerne deshydratée | X68: 5 | Y68: 0.54 | Z68: 103 | AA68: 91 | AB68: 1.7 | AC68: 5.9 | AD68: 17.5 | AE68: 29.5
C69: 30 kg | D69: 350 g | E69: Elevé | F69: femelle | G69: femelle de race à viande poids 30 kg - GMQ 350 g | H69: 1.07 | I69: 119 | J69: 4 | K69: 11.1 | L69: 110 | P69: =U15 -> 0 | Q69: =VLOOKUP(W15,$W$44:$AE$93,9) -> #N/A | R69: =IF(P69=0,0,(Q69/100)*(P69/100)) -> 0 | W69: Maïs grain | X69: 2 | Y69: 1.06 | Z69: 64 | AA69: 84 | AB69: 1.9 | AC69: 0.3 | AD69: 9.4 | AE69: 2.5
C70: 30 kg | D70: 400 g | E70: Elevé | F70: femelle | G70: femelle de race à viande poids 30 kg - GMQ 400 g | H70: ND | I70: ND | J70: ND | K70: ND | L70: 111 | P70: =U17 -> 0 | Q70: =VLOOKUP(W17,$W$44:$AE$93,9) -> #N/A | R70: =IF(P70=0,0,(Q70/100)*(P70/100)) -> 0 | W70: Mélasse | X70: 13 | Y70: 0.75 | Z70: 63 | AA70: 54 | AB70: 0.2 | AC70: 0.4 | AD70: 14.5 | AE70: 0
C71: 30 kg | D71: 450 g | E71: Elevé | F71: femelle | G71: femelle de race à viande poids 30 kg - GMQ 450 g | H71: ND | I71: ND | J71: ND | K71: ND | L71: 112 | P71: =U19 -> 0 | Q71: =VLOOKUP(W19,$W$44:$AE$93,9) -> #N/A | R71: =IF(P71=0,0,(Q71/100)*(P71/100)) -> 0 | W71: Orge | X71: 9 | Y71: 0.93 | Z71: 69 | AA71: 87 | AB71: 2.6 | AC71: 0.4 | AD71: 11.6 | AE71: 5.2
C72: 35 kg | D72: 150 g | E72: Elevé | F72: femelle | G72: femelle de race à viande poids 35 kg - GMQ 150 g | H72: 1.01 | I72: 73 | J72: 2.8 | K72: 6.5 | L72: 134 | W72: Pois | X72: 7 | Y72: 1.05 | Z72: 130 | AA72: 83 | AB72: 2.9 | AC72: 0.6 | AD72: 23.9 | AE72: 6
C73: 35 kg | D73: 200 g | E73: Elevé | F73: femelle | G73: femelle de race à viande poids 35 kg - GMQ 200 g | H73: 1.07 | I73: 84 | J73: 3.2 | K73: 8 | L73: 135 | W73: Poudre de lait écrémé | X73: 3 | Y73: 1.17 | Z73: 196 | AA73: 75 | AB73: 9.2 | AC73: 11.1 | AD73: 36 | AE73: 0
C74: 35 kg | D74: 250 g | E74: Elevé | F74: femelle | G74: femelle de race à viande poids 35 kg - GMQ 250 g | H74: 1.15 | I74: 96 | J74: 3.6 | K74: 9.5 | L74: 136 | Q74: =SUM(R66:R71)*100 -> 0 | R74: CB | W74: Pulpe de betterave | X74: 5 | Y74: 0.87 | Z74: 59 | AA74: 97 | AB74: 0.8 | AC74: 2.7 | AD74: 9.1 | AE74: 19.4
C75: 35 kg | D75: 300 g | E75: Elevé | F75: femelle | G75: femelle de race à viande poids 35 kg - GMQ 300 g | H75: 1.18 | I75: 107 | J75: 4 | K75: 10.5 | L75: 137 | W75: Sarrazin | Y75: 0.76 | Z75: 77 | AA75: 82 | AB75: 2.3 | AC75: 0.4 | AD75: 13.1 | AE75: 11.6
C76: 35 kg | D76: 350 g | E76: Elevé | F76: femelle | G76: femelle de race à viande poids 35 kg - GMQ 350 g | H76: 1.21 | I76: 118 | J76: 4.4 | K76: 12.4 | L76: 138 | W76: Seigle | X76: 5 | Y76: 1.03 | Z76: 59 | AA76: 85 | AB76: 2.3 | AC76: 0.6 | AD76: 10.3 | AE76: 2.2
C77: 35 kg | D77: 400 g | E77: Elevé | F77: femelle | G77: femelle de race à viande poids 35 kg - GMQ 400 g | H77: 1.23 | I77: 130 | J77: 4.8 | K77: 13.9 | L77: 139 | W77: Sorgho | X77: 4 | Y77: 1.06 | Z77: 67 | AA77: 87 | AB77: 2.1 | AC77: 0.2 | AD77: 109 | AE77: 2.7
C78: 35 kg | D78: 450 g | E78: Elevé | F78: femelle | G78: femelle de race à viande poids 35 kg - GMQ 450 g | H78: ND | I78: ND | J78: ND | K78: ND | L78: 140 | W78: Tourteau d'arachide | X78: 17 | Y78: 0.97 | Z78: 347 | AA78: 215 | AB78: 3.7 | AC78: 1.1 | AD78: 54.6 | AE78: 7.6
C79: 40 kg | D79: 150 g | E79: Elevé | F79: femelle | G79: femelle de race à viande poids 40 kg - GMQ 150 g | H79: ND | I79: ND | J79: ND | K79: ND | L79: 162 | W79: Tourteau de colza | X79: 7 | Y79: 0.8 | Z79: 219 | AA79: 138 | AB79: 8.2 | AC79: 4.6 | AD79: 35 | AE79: 13.9
C80: 40 kg | D80: 200 g | E80: Elevé | F80: femelle | G80: femelle de race à viande poids 40 kg - GMQ 200 g | H80: 1.21 | I80: 76 | J80: 3.5 | K80: 9 | L80: 163 | W80: Tourteau de lin | X80: 19 | Y80: 0.84 | Z80: 227 | AA80: 179 | AB80: 5.3 | AC80: 2.5 | AD80: 35.9 | AE80: 11
C81: 40 kg | D81: 250 g | E81: Elevé | F81: femelle | G81: femelle de race à viande poids 40 kg - GMQ 250 g | H81: 1.31 | I81: 87 | J81: 3.9 | K81: 10.5 | L81: 164 | W81: Tourteau de soja | X81: 18 | Y81: 1.05 | Z81: 331 | AA81: 229 | AB81: 4.4 | AC81: 1.8 | AD81: 51.6 | AE81: 6.8
C82: 40 kg | D82: 300 g | E82: Elevé | F82: femelle | G82: femelle de race à viande poids 40 kg - GMQ 300 g | H82: 1.36 | I82: 99 | J82: 4.4 | K82: 12 | L82: 165 | W82: Tourteau de tournesol | X82: 27 | Y82: 0.46 | Z82: 178 | AA82: 93 | AB82: 6.6 | AC82: 2.1 | AD82: 37.3 | AE82: 23.6
C83: 40 kg | D83: 350 g | E83: Elevé | F83: femelle | G83: femelle de race à viande poids 40 kg - GMQ 350 g | H83: 1.4 | I83: 100 | J83: 4.8 | K83: 13.6 | L83: 166 | W83: Triticale | X83: 6 | Y83: 1.02 | Z83: 63 | AA83: 84 | AB83: 2.6 | AC83: 0.4 | AD83: 11 | AE83: 2.7
C84: 40 kg | D84: 400 g | E84: Elevé | F84: femelle | G84: femelle de race à viande poids 40 kg - GMQ 400 g | H84: 1.43 | I84: 121 | J84: 5.2 | K84: 15.3 | L84: 167 | W84: Urée | X84: 0 | Y84: 0 | Z84: 1443 | AA84: 0 | AB84: 0 | AC84: 0 | AD84: 0 | AE84: 0
C85: 40 kg | D85: 450 g | E85: Elevé | F85: femelle | G85: femelle de race à viande poids 40 kg - GMQ 450 g | H85: ND | I85: ND | J85: ND | K85: ND | L85: 168 | W85: Vesce | Y85: 1.01 | Z85: 161 | AA85: 90 | AB85: 3.4 | AC85: 0.9 | AD85: 29.6 | AE85: 7.4
C86: 15 kg | D86: 150 g | E86: Modéré | F86: femelle | G86: femelle de race rustique ou croisée poids 15 kg - GMQ 150 g | H86: 0.68 | I86: 62 | J86: 1.7 | K86: 4.2 | L86: 8
C87: 15 kg | D87: 200 g | E87: Modéré | F87: femelle | G87: femelle de race rustique ou croisée poids 15 kg - GMQ 200 g | H87: 0.69 | I87: 75 | J87: 2.1 | K87: 5.3 | L87: 9
C88: 15 kg | D88: 250 g | E88: Modéré | F88: femelle | G88: femelle de race rustique ou croisée poids 15 kg - GMQ 250 g | H88: 0.71 | I88: 87 | J88: 2.5 | K88: 6.4 | L88: 10
C89: 15 kg | D89: 300 g | E89: Modéré | F89: femelle | G89: femelle de race rustique ou croisée poids 15 kg - GMQ 300 g | H89: ND | I89: ND | J89: 2.9 | K89: ND | L89: 11
C90: 15 kg | D90: 350 g | E90: Modéré | F90: femelle | G90: femelle de race rustique ou croisée poids 15 kg - GMQ 350 g | H90: ND | I90: ND | J90: ND | K90: ND | L90: 12
C91: 15 kg | D91: 400 g | E91: Modéré | F91: femelle | G91: femelle de race rustique ou croisée poids 15 kg - GMQ 400 g | H91: ND | I91: ND | J91: ND | K91: ND | L91: 13
C92: 15 kg | D92: 450 g | E92: Modéré | F92: femelle | G92: femelle de race rustique ou croisée poids 15 kg - GMQ 450 g | H92: ND | I92: ND | J92: ND | K92: ND | L92: 14
C93: 20 kg | D93: 150 g | E93: Modéré | F93: femelle | G93: femelle de race rustique ou croisée poids 20 kg - GMQ 150 g | H93: 0.8 | I93: 65 | J93: 1.9 | K93: 4.6 | L93: 36
C94: 20 kg | D94: 200 g | E94: Modéré | F94: femelle | G94: femelle de race rustique ou croisée poids 20 kg - GMQ 200 g | H94: 0.84 | I94: 78 | J94: 2.3 | K94: 5.7 | L94: 37
C95: 20 kg | D95: 250 g | E95: Modéré | F95: femelle | G95: femelle de race rustique ou croisée poids 20 kg - GMQ 250 g | H95: 0.89 | I95: 90 | J95: 2.7 | K95: 6.8 | L95: 38
C96: 20 kg | D96: 300 g | E96: Modéré | F96: femelle | G96: femelle de race rustique ou croisée poids 20 kg - GMQ 300 g | H96: 0.91 | I96: 103 | J96: 3 | K96: 8 | L96: 39
C97: 20 kg | D97: 350 g | E97: Modéré | F97: femelle | G97: femelle de race rustique ou croisée poids 20 kg - GMQ 350 g | H97: ND | I97: ND | J97: ND | K97: ND | L97: 40
C98: 20 kg | D98: 400 g | E98: Modéré | F98: femelle | G98: femelle de race rustique ou croisée poids 20 kg - GMQ 400 g | H98: ND | I98: ND | J98: ND | K98: ND | L98: 41
C99: 20 kg | D99: 450 g | E99: Modéré | F99: femelle | G99: femelle de race rustique ou croisée poids 20 kg - GMQ 450 g | H99: ND | I99: ND | J99: ND | K99: ND | L99: 42
C100: 25 kg | D100: 150 g | E100: Modéré | F100: femelle | G100: femelle de race rustique ou croisée poids 25 kg - GMQ 150 g | H100: 0.92 | I100: 68 | J100: 2.2 | K100: 5.2 | L100: 64
C101: 25 kg | D101: 200 g | E101: Modéré | F101: femelle | G101: femelle de race rustique ou croisée poids 25 kg - GMQ 200 g | H101: 0.98 | I101: 80 | J101: 2.6 | K101: 6.4 | L101: 65
C102: 25 kg | D102: 250 g | E102: Modéré | F102: femelle | G102: femelle de race rustique ou croisée poids 25 kg - GMQ 250 g | H102: 1.06 | I102: 91 | J102: 3 | K102: 7.6 | L102: 66
C103: 25 kg | D103: 300 g | E103: Modéré | F103: femelle | G103: femelle de race rustique ou croisée poids 25 kg - GMQ 300 g | H103: 1.1 | I103: 103 | J103: 3.3 | K103: 8.9 | L103: 67
C104: 25 kg | D104: 350 g | E104: Modéré | F104: femelle | G104: femelle de race rustique ou croisée poids 25 kg - GMQ 350 g | H104: ND | I104: ND | J104: ND | K104: ND | L104: 68
C105: 25 kg | D105: 400 g | E105: Modéré | F105: femelle | G105: femelle de race rustique ou croisée poids 25 kg - GMQ 400 g | H105: ND | I105: ND | J105: ND | K105: ND | L105: 69
C106: 25 kg | D106: 450 g | E106: Modéré | F106: femelle | G106: femelle de race rustique ou croisée poids 25 kg - GMQ 450 g | H106: ND | I106: ND | J106: ND | K106: ND | L106: 70
C107: 30 kg | D107: 150 g | E107: Modéré | F107: femelle | G107: femelle de race rustique ou croisée poids 30 kg - GMQ 150 g | H107: 1.04 | I107: 70 | J107: 2.4 | K107: 5.8 | L107: 92
C108: 30 kg | D108: 200 g | E108: Modéré | F108: femelle | G108: femelle de race rustique ou croisée poids 30 kg - GMQ 200 g | H108: 1.13 | I108: 81 | J108: 2.8 | K108: 7.1 | L108: 93
C109: 30 kg | D109: 250 g | E109: Modéré | F109: femelle | G109: femelle de race rustique ou croisée poids 30 kg - GMQ 250 g | H109: 1.23 | I109: 93 | J109: 3.2 | K109: 8.5 | L109: 94
C110: 30 kg | D110: 300 g | E110: Modéré | F110: femelle | G110: femelle de race rustique ou croisée poids 30 kg - GMQ 300 g | H110: 1.25 | I110: 104 | J110: 3.6 | K110: 9.7 | L110: 95
...

Sheet PATURAGE
B1: ALIM'ovins(v. 5.1)
B2: Rationnement des ovins
G4: Pâturage
C6: Saisissez la surface et le nombre d'animaux. Saisir les hauteurs d'herbe mesurées et prévues
B7: Surface de la parcelle | D7: ha | E7: Hauteur d'herbe à l'entrée | H7: cm* | J7: Hauteur de sortie prévue | N7: cm
B9: Nombre de femelles | G9: densité | K9: Nombre de jours de pâturage d'avance
G10: de la
B11: Catégorie | G11: prairie
C12: =IF(C11="","",CONCATENATE(N23," kg MS /jour")) | F12: Pousse de l'herbe ** | K12: =IF(C7="","",IF(H31=1,(C13/C16),IF(H31=2,(C13/C16)*1.07,IF(H31=3,(C13/C16)*1.15,(C13/C16)*1.3)))) | M12: =IF(K12="","","Jours")
B13: Quantité disponible | C13: =IF(C7="","",(G7-L7)*I23*C7) | D13: kg MS
C14: =IF(C7="","",CONCATENATE((C13/C7)/1000," t MS /ha")) | L14: =IF(K12="","",(C9*0.15)/C7) | M14: =IF(K12="","","UGB / ha")
C15: =IF(C8="","",CONCATENATE((C14/C8)/1000," t MS /ha")) | F15: * Hauteur d'herbe mesurée avec l'herbomètre ** Estimation de la pousse de l'herbe en fonction de la saison | K15: =IF(G7>13,"Trop de gaspillage Il vaut mieux faucher !",IF(C7="","",IF(J32>J33*1.2,"Risques de gaspillage importants: Augmentez le chargement !","")))
B16: Besoin d'herbe quotidien | C16: =IF(C7="","",N23*C9) | D16: kg MS
H22: Densité | L22: Besoins
C23: Brebis vide | H23: 2 | I23: =IF(H23=1,250,IF(H23=2,300,350)) -> 300 | L23: =C11 -> 0 | N23: =IF(L23="Brebis allaitante",3.5,IF(L23="Agnelle",2,2.5)) -> 2.5
C24: Brebis gestante
C25: Brebis allaitante | H25: pousse
C26: Agnelle | H26: Nulle (Hiver - Sécheresse)
C27: Bélier | H27: Faible (Eté) | M27: =IF(H31=1,(C13/C16),IF(H31=2,(C13/C16)*1.07,IF(H31=3,(C13/C16)*1.15,(C13/C16)*1.3))) -> #VALUE!
H28: Moyenne (Automne)
H29: Forte (Printemps)
H31: 1 | J31: =IF(H31=1,0,IF(H31=2,0.5,IF(H31=3,1,2))) -> 0
H32: =J32/C16 -> #VALUE! | J32: =(J31*I23*C7)/7 -> 0
H33: =H32*(K12/7) -> #VALUE! | J33: =C16
H34: =H33/K12 -> #VALUE!

Sheet NOUVEAU
B1: ALIM'ovins(v. 5.1) | R1: LISTE DE VOS ALIMENTS FOURRAGES CONCENTRES
B2: Rationnement des ovins | R2: =IF(E22="","",E22) -> Betterave fourragère | T2: =IF(R22="","",R22) -> ACL 40
R3: =IF(E23="","",E23) -> Foin de crau | T3: =IF(R23="","",R23)
I4: Nouveaux | R4: =IF(E24="","",E24) | T4: =IF(R24="","",R24) -> Epeautre
R5: =IF(E25="","",E25) | T5: =IF(R25="","",R25)
B6: VALEURS ALIMENTAIRES DE VOS ALIMENTS | R6: =IF(E26="","",E26) | T6: =IF(R26="","",R26)
R7: =IF(E27="","",E27) | T7: =IF(R27="","",R27)
B8: Les valeurs seront reportées automatiquement dans les listes d'aliments disponibles aux rubriques "Mon fourrage" et "Mon concentré" | R8: =IF(E28="","",E28) | T8: =IF(R28="","",R28)
G9: Valeurs alimentaires / kg | R9: =IF(E29="","",E29) | T9: =IF(R29="","",R29)
G10: Saisissez les valeurs alimentaires | R10: =IF(E30="","",E30) | T10: =IF(R30="","",R30)
E11: Saisir le nom de l'aliment | G11: % MS | H11: UEM | I11: UFL | J11: UFV | K11: PDIN | L11: PDIE | M11: Pabs | N11: Caabs | R11: =IF(E31="","",E31) | T11: =IF(R31="","",R31)
C12: FOURRAGE | R12: Maximum 7 fourrages | T12: Maximum 8 concentrés
E13: Saisir le nom de l'aliment | G13: UFL | H13: UFV | I13: PDIN | J13: PDIE | K13: Pabs | L13: Caabs | M13: MAT | N13: CB | R13: Pour supprimer un aliment, choisissez dans la liste | T13: Pour supprimer un aliment, choisissez dans la liste
C14: CONCENTRE
E15: N'oubliez pas de valider l'aliment
C16: =IF(PREVISION!D12=""," Si vous ne connaissez pas les valeurs UF et PDI de l'aliment, cliquez sur PREVISION","Rappel des valeurs alimentaires calculées (PREVISION)") -> Si vous ne connaissez pas les valeurs UF et PDI de l'aliment, cliquez sur PREVISION | I16: =IF(PREVISION!D12="","","UFL") | J16: =IF(PREVISION!D12="","","UFV") | K16: =IF(PREVISION!D12="","","PDIN") | L16: =IF(PREVISION!D12="","","PDIE") | M16: =IF(PREVISION!D12="","","P") | N16: =IF(PREVISION!D12="","","Ca")
I17: =PREVISION!J12 | J17: =PREVISION!J14 | K17: =PREVISION!J18 | L17: =PREVISION!J20 | M17: =PREVISION!N18 | N17: =PREVISION!N20
E20: TABLE DE VOS ALIMENTS
E21: FOURRAGE | G21: % MS | H21: U.E.M.. | I21: U.F.L. | J21: U.F.V. | K21: P.D.I.N. | L21: P.D.I.E. | M21: Pabs | N21: Caabs | R21: CONCENTRE | T21: U.F.L. | U21: U.F.V. | V21: P.D.I.N. | W21: P.D.I.E. | X21: Pabs | Y21: Caabs | Z21: MAT | AA21: CB
E22: Betterave fourragère | G22: 13 | H22: 0.91 | I22: 1.15 | J22: 1.16 | K22: 62 | L22: 86 | M22: 1.1 | N22: 0.5 | R22: ACL 40 | T22: 0.63 | U22: 0.62 | V22: 166 | W22: 114 | X22: 1 | Y22: 2 | Z22: 40 | AA22: 1
E23: Foin de crau | G23: 85 | H23: 1.37 | I23: 0.77 | J23: 0.69 | K23: 75 | L23: 87 | M23: 2 | N23: 3.7
R24: Epeautre | T24: 0.85 | U24: 0.82 | V24: 66 | W24: 82 | X24: 2.5 | Y24: 0.5 | Z24: 12 | AA24: 12.7

Sheet STOCKS
B1: ALIM'ovins(v. 5.1)
B2: Rationnement des ovins
F4: BILAN FOURRAGER
B6: EVALUATION DES STOCKS DISPONIBLES
B7: Saisissez les surfaces et les rendements ou les quantités (en bottes ou m3)
G8: Rendement (t MS/ha) | K8: Nombre de bottes | Q8: Poids d'une botte (kg) | S8: % MS | U8: Type | W8: Total MS
E9: Surface (ha) | I9: OU | K9: Produites | M9: Achetées | O9: Stocks (n-1)
B10: Foin balle ronde | I10: =IF(G10="",IF(E10="","",(K10*Q10*(S10/100))/(E10*1000)),"") | Q10: 260 | S10: 85 | U10: =IF(Q10<150,"90 x 90",IF(Q10>260,"150 x 150","120 x 120")) -> 120 x 120 | W10: =IF(G10="",IF(K10+M10+O10=0,"",(((K10+M10+O10)*Q10)*S10)/100000),(G10*E10)+(((M10+O10)*Q10)*S10)/100000) | X10: =IF(W10="","","t de MS")
B12: Autre | I12: =IF(G12="",IF(E12="","",(K12*Q12*(S12/100))/(E12*1000)),"") | Q12: 260 | S12: 85 | U12: =IF(Q12<150,"90 x 90",IF(Q12>260,"150 x 150","120 x 120")) -> 120 x 120 | W12: =IF(G12="",IF(K12+M12+O12=0,"",(((K12+M12+O12)*Q12)*S12)/100000),(G12*E12)+(((M12+O12)*Q12)*S12)/100000) | X12: =IF(W12="","","t de MS")
B14: Foin haute densité | I14: =IF(G14="",IF(E14="","",(K14*Q14*(S14/100))/(E14*1000)),"") | Q14: 400 | S14: 85 | U14: =IF(Q14<400,"80 x 90",IF(Q14>500,"120 x 90","120 x 130")) -> 120 x 130 | W14: =IF(G14="",IF(K14+M14+O14=0,"",(((K14+M14+O14)*Q14)*S14)/100000),(G14*E14)+(((M14+O14)*Q14)*S14)/100000) | X14: =IF(W14="","","t de MS")
B16: Paille alimentaire | I16: =IF(G16="",IF(E16="","",(K16*Q16*(S16/100))/(E16*1000)),"") | Q16: 180 | S16: 85 | U16: =IF(Q16<100,"90 x 90",IF(Q16>160,"150 x 150","120 x 120")) -> 150 x 150 | W16: =IF(G16="",IF(K16+M16+O16=0,"",(((K16+M16+O16)*Q16)*S16)/100000),(G16*E16)+(((M16+O16)*Q16)*S16)/100000) | X16: =IF(W16="","","t de MS")
B18: Enrubannage | I18: =IF(G18="",IF(E18="","",(K18*Q18*(S18/100))/(E18*1000)),"") | Q18: 400 | S18: 50 | U18: 120 x 120 | W18: =IF(G18="",IF(K18+M18+O18=0,"",(((K18+M18+O18)*Q18)*S18)/100000),(G18*E18)+(((M18+O18)*Q18)*S18)/100000) | X18: =IF(W18="","","t de MS")
G20: Rendement (t MS/ha) | K20: Volumes (m3)
E21: Surface (ha) | I21: OU | K21: Produits | M21: Achetés | O21: Stocks (n-1) | Q21: hauteur silo (cm) | S21: % MS | T21: Densité (kg MS/ m3)
B22: Ensilage herbe (couloir) | I22: =IF(G22="",IF(E22="","",(K22*Q22*(S22/100))/(E22*1000)),"") | Q22: 200 | S22: 30 | U22: =(5*S22)+(16*(Q22/100))+34 -> 216 | W22: =IF(G22="",IF(K22+M22+O22=0,"",(((K22+M22+O22)*Q22)*S22)/100000),(G22*E22)+(((M22+O22)*Q22)*S22)/100000) | X22: =IF(W22="","","t de MS")
B24: Ensilage herbe (taupe) | I24: =IF(G24="",IF(E24="","",(K24*Q24*(S24/100))/(E24*1000)),"") | Q24: 200 | S24: 30 | U24: =(5*S24)+(16*(Q24/100))+34 -> 216 | W24: =IF(G24="",IF(K24+M24+O24=0,"",(((K24+M24+O24)*Q24)*S24)/100000),(G24*E24)+(((M24+O24)*Q24)*S24)/100000) | X24: =IF(W24="","","t de MS")
B26: Ensilage maïs | I26: =IF(G26="",IF(E26="","",(K26*Q26*(S26/100))/(E26*1000)),"") | Q26: 200 | S26: 30 | U26: =(5*S26)+(16*(Q26/100))+34 -> 216 | W26: =IF(G26="",IF(K26+M26+O26=0,"",(((K26+M26+O26)*Q26)*S26)/100000),(G26*E26)+(((M26+O26)*Q26)*S26)/100000) | X26: =IF(W26="","","t de MS")
B28: Autre | I28: =IF(G28="",IF(E28="","",(K28*Q28*(S28/100))/(E28*1000)),"") | Q28: 200 | S28: 30 | U28: =(5*S28)+(16*(Q28/100))+34 -> 216 | W28: =IF(G28="",IF(K28+M28+O28=0,"",(((K28+M28+O28)*Q28)*S28)/100000),(G28*E28)+(((M28+O28)*Q28)*S28)/100000) | X28: =IF(W28="","","t de MS")
B30: Autre | I30: =IF(G30="",IF(E30="","",(K30*Q30*(S30/100))/(E30*1000)),"") | Q30: 130 | S30: 30 | U30: =(5*S30)+(16*(Q30/100))+34 -> 204.8 | W30: =IF(G30="",IF(K30+M30+O30=0,"",(((K30+M30+O30)*Q30)*S30)/100000),(G30*E30)+(((M30+O30)*Q30)*S30)/100000) | X30: =IF(W30="","","t de MS")
B32: Autre | I32: =IF(G32="",IF(E32="","",(K32*Q32*(S32/100))/(E32*1000)),"") | Q32: 190 | S32: 30 | U32: =(5*S32)+(16*(Q32/100))+34 -> 214.4 | W32: =IF(G32="",IF(K32+M32+O32=0,"",(((K32+M32+O32)*Q32)*S32)/100000),(G32*E32)+(((M32+O32)*Q32)*S32)/100000) | X32: =IF(W32="","","t de MS")
B34: Foin vrac | I34: =IF(G34="",IF(E34="","",(K34*U34*(S34/100))/(E34*1000)),"") | S34: 85 | U34: 90 | W34: =IF(G34="",IF(K34+M34+O34=0,"",(((K34+M34+U34)*Q34)*S34)/100000),(G34*E34)+(((M34+O34)*U34)*S34)/100000) | X34: =IF(W34="","","t de MS")
B41: 90 x 90 | O41: 1 | Q41: 120 | S41: 80 | U41: 80
B42: 120 x 120 | O42: 1.2 | Q42: 200 | S42: 120 | U42: 85
B43: 150 x 150 | O43: 1.5 | Q43: 280 | S43: 180 | U43: 90
B44: 180 x 180 | O44: 1.7 | Q44: 400 | S44: 300 | U44: 95
O45: 2
O46: 2.2 | Q46: 300 | S46: 20 | U46: 40
O47: 2.5 | Q47: 350 | S47: 25 | U47: 45
Q48: 400 | S48: 30 | U48: 50
Q49: 450 | S49: 35 | U49: 55
Q50: 500 | S50: 40 | U50: 60
Q51: 550 | S51: 45
Q52: 600

Sheet BESOINS
B1: ALIM'ovins(v. 5.1)
B2: Rationnement des ovins
B4: BILAN FOURRAGER
B6: EVALUATION DES BESOINS | R6: BILAN
B8: Lot | D8: Catégorie | F8: Effectif | H8: U.G.B | J8: Consommation (kg MS/j) | L8: Durée (jours) | N8: Besoins en MS | R8: Stocks disponibles | U8: =IF(SUM(STOCKS!W10:W34)=0,"",IF(STOCKS!W16="",SUM(STOCKS!W10:W34),SUM(STOCKS!W10:W34)-STOCKS!W16)) | W8: =IF(U8="","","t de MS")
B9: Lot N°1 | H9: =IF(D9="","",VLOOKUP(D9,$D$41:$F$50,3)) | J9: =IF(D9="","",VLOOKUP(D9,$D$41:$E$50,2)) | N9: =IF(D9="","",(F9*J9*L9)/1000) | O9: =IF(D9="","","t de MS")
R10: Besoins du troupeau | U10: =IF(SUM(N9:N27)=0,"",SUM(N9:N27)) | W10: =IF(U10="","","t de MS")
B11: Lot N°2 | H11: =IF(D11="","",VLOOKUP(D11,$D$41:$F$50,3)) | J11: =IF(D11="","",VLOOKUP(D11,$D$41:$E$50,2)) | N11: =IF(D11="","",(F11*J11*L11)/1000) | O11: =IF(D11="","","t de MS")
B13: Lot N°3 | H13: =IF(D13="","",VLOOKUP(D13,$D$41:$F$50,3)) | J13: =IF(D13="","",VLOOKUP(D13,$D$41:$E$50,2)) | N13: =IF(D13="","",(F13*J13*L13)/1000) | O13: =IF(D13="","","t de MS") | R13: Marge de sécurité | T13: =(V13*52)/100 -> 4.16 | U13: semaine(s) | V13: 8 | W13: %
B15: Lot N°4 | H15: =IF(D15="","",VLOOKUP(D15,$D$41:$F$50,3)) | J15: =IF(D15="","",VLOOKUP(D15,$D$41:$E$50,2)) | N15: =IF(D15="","",(F15*J15*L15)/1000) | O15: =IF(D15="","","t de MS") | R15: BILAN FOURRAGER ( hors paille) | U15: =IF(SUM(STOCKS!W10:W34)=0,"",IF(U10="","",U8-(U10*(1+(V13/100))))) | W15: =IF(U15="","","t de MS")
B17: Lot N°5 | H17: =IF(D17="","",VLOOKUP(D17,$D$41:$F$50,3)) | J17: =IF(D17="","",VLOOKUP(D17,$D$41:$E$50,2)) | N17: =IF(D17="","",(F17*J17*L17)/1000) | O17: =IF(D17="","","t de MS")
R18: en pourcentage des besoins | U18: =IF(U15="","",U15/U10)
B19: Lot N°6 | H19: =IF(D19="","",VLOOKUP(D19,$D$41:$F$50,3)) | J19: =IF(D19="","",VLOOKUP(D19,$D$41:$E$50,2)) | N19: =IF(D19="","",(F19*J19*L19)/1000) | O19: =IF(D19="","","t de MS")
R20: =IF(U8="","",IF(U15<0,"Attention ! votre bilan fourrager est déficitaire",IF(U15>10,"Votre bilan fourrager est excédentaire","Votre bilan fourrager est équilibré")))
B21: Lot N°7 | H21: =IF(D21="","",VLOOKUP(D21,$D$41:$F$50,3)) | J21: =IF(D21="","",VLOOKUP(D21,$D$41:$E$50,2)) | N21: =IF(D21="","",(F21*J21*L21)/1000) | O21: =IF(D21="","","t de MS")
B23: Lot N°8 | H23: =IF(D23="","",VLOOKUP(D23,$D$41:$F$50,3)) | J23: =IF(D23="","",VLOOKUP(D23,$D$41:$E$50,2)) | N23: =IF(D23="","",(F23*J23*L23)/1000) | O23: =IF(D23="","","t de MS") | R23: BILAN FOURRAGER (avec paille) | U23: =IF(STOCKS!W16="",IF(SUM(STOCKS!W10:W34)=0,"",IF(U10="","",U8-(U10*(1+(V13/100))))),IF(SUM(STOCKS!W10:W34)=0,"",IF(U10="","",U15+STOCKS!W16))) | W23: =IF(U23="","","t de MS")
B25: Lot N°9 | H25: =IF(D25="","",VLOOKUP(D25,$D$41:$F$50,3)) | J25: =IF(D25="","",VLOOKUP(D25,$D$41:$E$50,2)) | N25: =IF(D25="","",(F25*J25*L25)/1000) | O25: =IF(D25="","","t de MS")
R26: en pourcentage des besoins | U26: =IF(U23="","",U23/U10)
B27: Lot N°10 | H27: =IF(D27="","",VLOOKUP(D27,$D$41:$F$50,3)) | J27: =IF(D27="","",VLOOKUP(D27,$D$41:$E$50,2)) | N27: =IF(D27="","",(F27*J27*L27)/1000) | O27: =IF(D27="","","t de MS")
D41: Agneau à l'engrais | E41: 0.5 | F41: 0.05
D42: Agnelle - 6 mois | E42: 0.5 | F42: 0.05
D43: Agnelle + 6 mois | E43: 1 | F43: 0.07 | S43: Brebis | T43: 0.15
D44: Bélier - 1 an | E44: 1.5 | F44: 0.15 | S44: Agnelles - 6 mois | T44: 0.05
D45: Bélier - 6 mois | E45: 1 | F45: 0.05 | S45: Agnelles 6 mois et + | T45: 0.07
D46: Bélier adulte | E46: 2.5 | F46: 0.15 | S46: Béliers - 6 mois | T46: 0.05
D47: Brebis allaitante | E47: 2 | F47: 0.15 | S47: Béliers 6 mois et + | T47: 0.15
D48: Brebis de réforme | E48: 2 | F48: 0.15 | S48: Mâle castré de +12 mois | T48: 0.15
D49: Brebis gestante | E49: 1.5 | F49: 0.15 | S49: Agneaux de boucherie | T49: 0.05
D50: Brebis traite | E50: 2 | F50: 0.15
D51: Brebis vide | E51: 2 | F51: 0.15
